Workbook

Sheet README
A1: Nabd — Hospital / Clinic Management System
A2: Implementation Task Plan v2 — rebuilt against the updated wireframe
A4: Prepared for | B4: Harish
A5: Date | B5: 13 August 2026
A6: Supersedes | B6: v1 of 11 August 2026 (202 tasks, 1,210 points)
A7: Source | B7: Nabd wireframe (Platform Console v29 + current shell) and DESIGN.md in the connected folder
A9: WHAT THE UPDATED WIREFRAME CHANGED
A10: The wireframe now carries a formal requirement register — 185 identifiers across 30 prefixes (SYS, PAT, CGV, CAD, RCP, OWN, PKG, BIL,
A11: PHR, CMP, DPO, SSA, SCS, AGG, CEO, NFR, MKT and nine clinical specialties). Every task below is traced to those identifiers, and the
A12: Requirement Coverage tab proves all 185 are covered.
A13: Four product areas exist now that did not exist in v1: the patient WhatsApp surface, caregiver and family handling, the aggregator layer,
A14: and a rebuilt platform console with seven distinct SaaS operator roles.
A15: DESIGN.md gained a full chart system (sections 8.22-8.29) and a messaging component set (8.16-8.21). Both are now build epics.
A16: Scope roughly doubled: 349 tasks and 2,260 points against v1's 202 and 1,210.
A18: EXPLICIT NON-GOALS TAKEN FROM THE WIREFRAME — do not build these
A19: NFR-06 | B19: No SSO and no hardware security keys. Staff sign in with WhatsApp OTP, a short PIN or an authenticator app. The v1 SSO/OIDC task has been deleted.
A20: CAD-10 | B20: No payroll engine. Payroll is a CSV export only.
A21: SYS-10 | B21: No live claims pipeline. Full claims go via certified middleware in Phase 3. Ayushman is out of scope. Only a simple claim export (BIL-11) and NPHIES eligibility-check-lite (RCP-07) are in scope.
A22: PHR-04 | B22: Controlled drugs get a warning and a register entry, never a hard block — no registered pharmacist licence is assumed.
A23: CEO-14 | B23: No review filtering or gating. Nabd and Google ratings are never blended into one number.
A24: CEO-25 | B24: Adherence data is capture-only and is never monetised.
A25: AGG-03 | B25: Word-to-specialty matching only. No symptom interpretation and no clinical triage.
A26: PED-04 | B26: Growth percentiles are never calculated in the UI — only a validated growth service may produce them.
A28: PLANNING ASSUMPTIONS — edit the blue cells; everything derived recalculates
A29: Assumption | B29: Value | C29: Note
A30: Sprint length (weeks) | B30: 2 | C30: Standard two-week iteration
A31: Velocity per squad (points / sprint) | B31: 40 | C31: A squad is roughly 6 people. Sprint capacity = this multiplied by the squads active that sprint.
A32: Person-days per story point | B32: 0.6 | C32: Calibrate after two or three sprints; drives the indicative effort column only.
A33: Blended cost per person-day | B33: 0 | C33: Optional — enter your rate to cost the plan. Left at zero by the author.
A34: Peak squads in parallel | B34: 5 | C34: Reached in sprints 14-18. Roughly 30 delivery people at peak — this scope cannot be absorbed by one team.
A37: TABS
A38: Tab | B38: Purpose
A39: Backlog | B39: The full task list — 349 rows. One row is one epic-level story. Edit Status, Sprint, Points and Owner.
A40: Requirement Coverage | B40: Every one of the 185 wireframe requirement identifiers mapped to the tasks that deliver it. Zero uncovered is the release gate.
A41: Epics | B41: Automatic rollup by epic. All formulas — do not type here.
A42: Sprints | B42: Sprint load against ramped squad capacity. Over-capacity sprints turn red.
A43: Tracks | B43: Rollup by parallel delivery track, showing how the four tracks are staffed.
A44: RBAC Matrix | B44: The clinic role and permission grid taken from the wireframe — the specification for epic E06.
A45: SaaS Operator Roles | B45: The seven platform-side roles from SSA-02 and what each may reach.
A46: Security Controls | B46: Cybersecurity, privacy and compliance controls mapped to delivering tasks, with a go-live gate counter.
A47: Risks | B47: Delivery, security and clinical-safety risks with owners and mitigations.
A48: Changes from v1 | B48: What was added, removed and re-scoped when the wireframe was updated.
A50: Estimates are the author's architectural judgement from the wireframe, not a quotation. They assume no pre-existing codebase.

Sheet Backlog
A1: ID | B1: Epic | C1: Module | D1: Task | E1: Description | F1: Requirement IDs | G1: Roles Impacted | H1: Track | I1: Discipline | J1: Priority | K1: Delivery Phase | L1: Story Points | M1: Sprint | N1: Release Band | O1: Est. Person-Days | P1: Depends On | Q1: Acceptance Criteria | R1: Status | S1: Owner / Squad
A2: NB-001 | B2: E01 Foundation & Architecture | C2: Architecture | D2: Define target architecture & ADR set | E2: Modular monolith + Postgres, region-isolated stacks for India and KSA, event bus for messaging. ADRs for datastore, tenancy, hosting. | F2: SYS-14,NFR-04 | G2: All | H2: Shared | I2: Architecture | J2: Must | K2: MVP | L2: 8 | M2: 1 | N2: =IF(M2<=4,"R1 Foundation",IF(M2<=8,"R2 Core Clinic",IF(M2<=13,"R3 Revenue & Messaging",IF(M2<=18,"R4 Patient & Platform",IF(M2<=20,"R5 Harden","R6 Launch"))))) | O2: =L2*README!$B$32 | Q2: ADRs approved; C4 L1/L2 published; region topology signed off | R2: Not started
A3: NB-002 | B3: E01 Foundation & Architecture | C3: Architecture | D3: Multi-tenancy isolation model + irreversible region lock | E3: Region is chosen at provisioning and locked permanently. No cross-region replication; region-scoped KMS keys. | F3: SYS-14,NFR-04 | G3: Platform | H3: Shared | I3: Architecture | J3: Must | K3: MVP | L3: 8 | M3: 1 | N3: =IF(M3<=4,"R1 Foundation",IF(M3<=8,"R2 Core Clinic",IF(M3<=13,"R3 Revenue & Messaging",IF(M3<=18,"R4 Patient & Platform",IF(M3<=20,"R5 Harden","R6 Launch"))))) | O3: =L3*README!$B$32 | P3: NB-001 | Q3: PoC proves row-level isolation; region field immutable after provisioning; attempt to change is rejected and audited | R3: Not started
A4: NB-003 | B4: E01 Foundation & Architecture | C4: Data | D4: Core data model & ERD | E4: Tenant, Clinic, Branch, Staff, Role, Patient, FamilyMember, Encounter, Appointment, Invoice, Package, Prescription, PharmacyItem, ConsentRecord, AuditEvent. | F4: SYS-13 | G4: All | H4: Shared | I4: Backend | J4: Must | K4: MVP | L4: 13 | M4: 1 | N4: =IF(M4<=4,"R1 Foundation",IF(M4<=8,"R2 Core Clinic",IF(M4<=13,"R3 Revenue & Messaging",IF(M4<=18,"R4 Patient & Platform",IF(M4<=20,"R5 Harden","R6 Launch"))))) | O4: =L4*README!$B$32 | P4: NB-001 | Q4: ERD reviewed; migrations generated; naming conventions documented | R4: Not started
A5: NB-004 | B5: E01 Foundation & Architecture | C5: Data | D5: Database migration framework & seed data | E5: Versioned reversible migrations; seed tenants for India and KSA demo clinics matching the wireframe fixtures. | G5: All | H5: Shared | I5: Backend | J5: Must | K5: MVP | L5: 3 | M5: 2 | N5: =IF(M5<=4,"R1 Foundation",IF(M5<=8,"R2 Core Clinic",IF(M5<=13,"R3 Revenue & Messaging",IF(M5<=18,"R4 Patient & Platform",IF(M5<=20,"R5 Harden","R6 Launch"))))) | O5: =L5*README!$B$32 | P5: NB-003 | Q5: Migrate up/down clean; seeds reproduce wireframe demo data | R5: Not started
A6: NB-005 | B6: E01 Foundation & Architecture | C6: API | D6: API standards, versioning & error contract | E6: REST /v1, RFC7807 errors, pagination, idempotency keys on every financial and clinical write. | F6: SYS-06 | G6: All | H6: Shared | I6: Backend | J6: Must | K6: MVP | L6: 5 | M6: 2 | N6: =IF(M6<=4,"R1 Foundation",IF(M6<=8,"R2 Core Clinic",IF(M6<=13,"R3 Revenue & Messaging",IF(M6<=18,"R4 Patient & Platform",IF(M6<=20,"R5 Harden","R6 Launch"))))) | O6: =L6*README!$B$32 | P6: NB-001 | Q6: OpenAPI published; CI linter enforces the standard | R6: Not started
A7: NB-006 | B7: E01 Foundation & Architecture | C7: API | D7: API gateway & per-role BFF layer | E7: Single entry point; role-shaped payloads so the mobile queue screen stays small. | F7: NFR-02 | G7: All | H7: Shared | I7: Backend | J7: Should | K7: MVP | L7: 5 | M7: 3 | N7: =IF(M7<=4,"R1 Foundation",IF(M7<=8,"R2 Core Clinic",IF(M7<=13,"R3 Revenue & Messaging",IF(M7<=18,"R4 Patient & Platform",IF(M7<=20,"R5 Harden","R6 Launch"))))) | O7: =L7*README!$B$32 | P7: NB-005 | Q7: p95 payload under 150KB on the queue screen | R7: Not started
A8: NB-007 | B8: E01 Foundation & Architecture | C8: Platform | D8: Event bus & transactional outbox | E8: No clinical, billing or messaging event may be lost. Drives WhatsApp, SMS, recall and webhooks. | F8: SYS-01,NFR-12 | G8: All | H8: Shared | I8: Backend | J8: Must | K8: MVP | L8: 8 | M8: 3 | N8: =IF(M8<=4,"R1 Foundation",IF(M8<=8,"R2 Core Clinic",IF(M8<=13,"R3 Revenue & Messaging",IF(M8<=18,"R4 Patient & Platform",IF(M8<=20,"R5 Harden","R6 Launch"))))) | O8: =L8*README!$B$32 | P8: NB-003, NB-005 | Q8: Zero message loss under forced consumer failure | R8: Not started
A9: NB-008 | B9: E01 Foundation & Architecture | C9: Platform | D9: Feature-flag & module-entitlement service | E9: Drives Included / Trial / Paid add-on / Upgrade required / Disabled-by-clinic / Disabled-by-platform states. | F9: SYS-20,CAD-13 | G9: Owner,Platform | H9: Shared | I9: Backend | J9: Must | K9: MVP | L9: 8 | M9: 3 | N9: =IF(M9<=4,"R1 Foundation",IF(M9<=8,"R2 Core Clinic",IF(M9<=13,"R3 Revenue & Messaging",IF(M9<=18,"R4 Patient & Platform",IF(M9<=20,"R5 Harden","R6 Launch"))))) | O9: =L9*README!$B$32 | P9: NB-001, NB-002 | Q9: Entitlement change propagates in under 60s; upgrade/downgrade under 5 minutes with no data loss | R9: Not started
A10: NB-009 | B10: E01 Foundation & Architecture | C10: Platform | D10: Config & secrets management with role separation | E10: Installation secrets are separate from tenant integration secrets — two different operator roles. | F10: SYS-14 | G10: All | H10: Shared | I10: DevOps | J10: Must | K10: MVP | L10: 5 | M10: 2 | N10: =IF(M10<=4,"R1 Foundation",IF(M10<=8,"R2 Core Clinic",IF(M10<=13,"R3 Revenue & Messaging",IF(M10<=18,"R4 Patient & Platform",IF(M10<=20,"R5 Harden","R6 Launch"))))) | O10: =L10*README!$B$32 | P10: NB-299 | Q10: Secret scan clean; installation and tenant secrets held in separate scopes with separate access | R10: Not started
A11: NB-010 | B11: E01 Foundation & Architecture | C11: Data | D11: Reference data service | E11: ICD-10 subset, drug master (India NMC generics + KSA SFDA identifiers), charge catalogue, GST/VAT rate tables, vaccine schedules. | F11: GP-05,DOC-06 | G11: Doctor,Reception | H11: Shared | I11: Backend | J11: Must | K11: MVP | L11: 8 | M11: 4 | N11: =IF(M11<=4,"R1 Foundation",IF(M11<=8,"R2 Core Clinic",IF(M11<=13,"R3 Revenue & Messaging",IF(M11<=18,"R4 Patient & Platform",IF(M11<=20,"R5 Harden","R6 Launch"))))) | O11: =L11*README!$B$32 | P11: NB-003 | Q11: Catalogue seeded; rates and drug lists versioned by effective date | R11: Not started
A12: NB-011 | B12: E01 Foundation & Architecture | C12: Platform | D12: Shared reason-code service | E12: One shared reason list reused by cancellation, reschedule, block, override and refusal flows. | F12: SYS-07 | G12: All | H12: Shared | I12: Backend | J12: Must | K12: MVP | L12: 3 | M12: 4 | N12: =IF(M12<=4,"R1 Foundation",IF(M12<=8,"R2 Core Clinic",IF(M12<=13,"R3 Revenue & Messaging",IF(M12<=18,"R4 Patient & Platform",IF(M12<=20,"R5 Harden","R6 Launch"))))) | O12: =L12*README!$B$32 | P12: NB-003 | Q12: Every reason-capture surface reads from this service; reasons are configurable per tenant | R12: Not started
A13: NB-012 | B13: E02 Design System & UI Kit | C13: Design System | D13: Tokenise DESIGN.md into a theme package | E13: All --nb-* colour, spacing, radius, elevation and motion tokens as a shared package. | G13: All | H13: Shared | I13: Frontend | J13: Must | K13: MVP | L13: 5 | M13: 1 | N13: =IF(M13<=4,"R1 Foundation",IF(M13<=8,"R2 Core Clinic",IF(M13<=13,"R3 Revenue & Messaging",IF(M13<=18,"R4 Patient & Platform",IF(M13<=20,"R5 Harden","R6 Launch"))))) | O13: =L13*README!$B$32 | Q13: Token package published; visual diff vs wireframe under 2px | R13: Not started
A14: NB-013 | B14: E02 Design System & UI Kit | C14: Design System | D14: Core controls — button, input, select, segmented, chip | E14: Per DESIGN.md 8.1-8.4 with every rest/hover/active/focus/disabled/loading state. | G14: All | H14: Shared | I14: Frontend | J14: Must | K14: MVP | L14: 8 | M14: 2 | N14: =IF(M14<=4,"R1 Foundation",IF(M14<=8,"R2 Core Clinic",IF(M14<=13,"R3 Revenue & Messaging",IF(M14<=18,"R4 Patient & Platform",IF(M14<=20,"R5 Harden","R6 Launch"))))) | O14: =L14*README!$B$32 | P14: NB-012 | Q14: Storybook covers every state; a11y checks pass | R14: Not started
A15: NB-014 | B15: E02 Design System & UI Kit | C15: Design System | D15: Containers — card, table, mobile list row, drawer, modal, bottom sheet | E15: Per 8.5-8.13 including the sub-768px table-to-card replacement. | G15: All | H15: Shared | I15: Frontend | J15: Must | K15: MVP | L15: 8 | M15: 2 | N15: =IF(M15<=4,"R1 Foundation",IF(M15<=8,"R2 Core Clinic",IF(M15<=13,"R3 Revenue & Messaging",IF(M15<=18,"R4 Patient & Platform",IF(M15<=20,"R5 Harden","R6 Launch"))))) | O15: =L15*README!$B$32 | P15: NB-012 | Q15: Responsive switch verified at 767/768px; focus trap correct | R15: Not started
A16: NB-015 | B16: E02 Design System & UI Kit | C16: Design System | D16: Clinical state system — pill, badge, critical shape cue | E16: Nine states, each hue + icon + text; critical adds a shape cue and a 3px left bar. | G16: All | H16: Shared | I16: Frontend | J16: Must | K16: MVP | L16: 5 | M16: 3 | N16: =IF(M16<=4,"R1 Foundation",IF(M16<=8,"R2 Core Clinic",IF(M16<=13,"R3 Revenue & Messaging",IF(M16<=18,"R4 Patient & Platform",IF(M16<=20,"R5 Harden","R6 Launch"))))) | O16: =L16*README!$B$32 | P16: NB-012 | Q16: Colour-blind simulation review passed; no hue-only state anywhere | R16: Not started
A17: NB-016 | B17: E02 Design System & UI Kit | C17: Design System | D17: Icon sprite & illustration tier | E17: Single monoline family at stroke 1.75; 3D illustration set reserved for empty and success states only. | G17: All | H17: Shared | I17: Frontend | J17: Must | K17: MVP | L17: 3 | M17: 2 | N17: =IF(M17<=4,"R1 Foundation",IF(M17<=8,"R2 Core Clinic",IF(M17<=13,"R3 Revenue & Messaging",IF(M17<=18,"R4 Patient & Platform",IF(M17<=20,"R5 Harden","R6 Launch"))))) | O17: =L17*README!$B$32 | P17: NB-012 | Q17: Sprite built from the wireframe symbols; lint blocks a second UI icon family | R17: Not started
A18: NB-017 | B18: E02 Design System & UI Kit | C18: Design System | D18: App shell — sidebar, sectioned nav, rail, top bar, bottom nav | E18: 248px sidebar / 72px collapsed / 88px rail / 64px bottom nav, with section grouping for the platform console. | F18: SSA-02 | G18: All | H18: Shared | I18: Frontend | J18: Must | K18: MVP | L18: 8 | M18: 3 | N18: =IF(M18<=4,"R1 Foundation",IF(M18<=8,"R2 Core Clinic",IF(M18<=13,"R3 Revenue & Messaging",IF(M18<=18,"R4 Patient & Platform",IF(M18<=20,"R5 Harden","R6 Launch"))))) | O18: =L18*README!$B$32 | P18: NB-014, NB-013 | Q18: Shell renders at all four breakpoints; nav sections group correctly | R18: Not started
A19: NB-018 | B19: E02 Design System & UI Kit | C19: Design System | D19: Messaging component set | E19: Message bubble, template card with variable-only editing, interactive reply set, conversation row, delivery-state chip, session-window indicator (8.16-8.21). | F19: RCP-11,CMP-07 | G19: All | H19: Shared | I19: Frontend | J19: Must | K19: MVP | L19: 8 | M19: 6 | N19: =IF(M19<=4,"R1 Foundation",IF(M19<=8,"R2 Core Clinic",IF(M19<=13,"R3 Revenue & Messaging",IF(M19<=18,"R4 Patient & Platform",IF(M19<=20,"R5 Harden","R6 Launch"))))) | O19: =L19*README!$B$32 | P19: NB-013, NB-014 | Q19: Template card makes fixed text physically uneditable; session indicator gates the composer | R19: Not started
A20: NB-019 | B20: E02 Design System & UI Kit | C20: Design System | D20: Command palette (Cmd/Ctrl-K) | E20: Grouped, role-scoped results. Platform console searches clinics, tickets, invoices and provisioning jobs. | G20: All | H20: Shared | I20: Frontend | J20: Should | K20: MVP | L20: 5 | M20: 8 | N20: =IF(M20<=4,"R1 Foundation",IF(M20<=8,"R2 Core Clinic",IF(M20<=13,"R3 Revenue & Messaging",IF(M20<=18,"R4 Patient & Platform",IF(M20<=20,"R5 Harden","R6 Launch"))))) | O20: =L20*README!$B$32 | P20: NB-017 | Q20: Only permitted entities appear for the signed-in role | R20: Not started
A21: NB-020 | B21: E02 Design System & UI Kit | C21: Design System | D21: Loading, empty, error, offline & permission state patterns | E21: Skeleton shimmer, 140px illustration empties, inline errors, sync banner, absent-not-disabled permission handling. | F21: NFR-12 | G21: All | H21: Shared | I21: Frontend | J21: Must | K21: MVP | L21: 5 | M21: 4 | N21: =IF(M21<=4,"R1 Foundation",IF(M21<=8,"R2 Core Clinic",IF(M21<=13,"R3 Revenue & Messaging",IF(M21<=18,"R4 Patient & Platform",IF(M21<=20,"R5 Harden","R6 Launch"))))) | O21: =L21*README!$B$32 | P21: NB-014 | Q21: Every list screen implements all states; no disabled element carries a permission reason | R21: Not started
A22: NB-021 | B22: E02 Design System & UI Kit | C22: Design System | D22: Light theme build | E22: DESIGN.md 1.7 mapping. Blocked on stakeholder approval — still marked NEEDS APPROVAL in the source. | G22: All | H22: Shared | I22: Frontend | J22: Could | K22: Phase 2 | L22: 5 | M22: 19 | N22: =IF(M22<=4,"R1 Foundation",IF(M22<=8,"R2 Core Clinic",IF(M22<=13,"R3 Revenue & Messaging",IF(M22<=18,"R4 Patient & Platform",IF(M22<=20,"R5 Harden","R6 Launch"))))) | O22: =L22*README!$B$32 | P22: NB-012 | Q22: Light theme passes AA on all tokens; per-user toggle persists | R22: Not started
A23: NB-022 | B23: E03 Chart & Data-Visualisation System | C23: Charts | D23: Chart colour foundation & series palette | E23: Eight categorical series in the OKLCH 0.49-0.53 band, sequential and diverging ramps, neutral diverging midpoint. Reserved state colours never appear as a series. | F23: GP-03,PED-03 | G23: All | H23: Shared | I23: Frontend | J23: Must | K23: MVP | L23: 8 | M23: 5 | N23: =IF(M23<=4,"R1 Foundation",IF(M23<=8,"R2 Core Clinic",IF(M23<=13,"R3 Revenue & Messaging",IF(M23<=18,"R4 Patient & Platform",IF(M23<=20,"R5 Harden","R6 Launch"))))) | O23: =L23*README!$B$32 | P23: NB-012 | Q23: All eight series at 3:1 on surface-1; automated check rejects any state colour used as series identity | R23: Not started
A24: NB-023 | B24: E03 Chart & Data-Visualisation System | C24: Charts | D24: All-pairs gate & series-count guard | E24: Only slots 1-3 clear the all-pairs gate; slots 4 and 6 must never share an all-pairs chart. Past three series, fold to Other or facet. | F24: GP-03 | G24: All | H24: Shared | I24: Frontend | J24: Must | K24: MVP | L24: 5 | M24: 5 | N24: =IF(M24<=4,"R1 Foundation",IF(M24<=8,"R2 Core Clinic",IF(M24<=13,"R3 Revenue & Messaging",IF(M24<=18,"R4 Patient & Platform",IF(M24<=20,"R5 Harden","R6 Launch"))))) | O24: =L24*README!$B$32 | P24: NB-022 | Q24: Component refuses a fourth series in scatter/bubble/small-multiple mode and folds to Other | R24: Not started
A25: NB-024 | B25: E03 Chart & Data-Visualisation System | C25: Charts | D25: Column, bar, line & area primitives | E25: Inline SVG only, no charting library, no canvas. 24px max thickness, 2px surface gap, 2px line, markers with surface ring. | F25: NFR-02 | G25: All | H25: Shared | I25: Frontend | J25: Must | K25: MVP | L25: 8 | M25: 6 | N25: =IF(M25<=4,"R1 Foundation",IF(M25<=8,"R2 Core Clinic",IF(M25<=13,"R3 Revenue & Messaging",IF(M25<=18,"R4 Patient & Platform",IF(M25<=20,"R5 Harden","R6 Launch"))))) | O25: =L25*README!$B$32 | P25: NB-022 | Q25: No third-party chart library in the bundle; renders under budget on a mid-range Android | R25: Not started
A26: NB-025 | B26: E03 Chart & Data-Visualisation System | C26: Charts | D26: Stat tile, meter & sparkline | E26: Auto-compacted values (1,284 / 12.9K / Rs 4.2L), signed delta coloured by direction and whether up is good. | F26: OWN-01 | G26: Owner | H26: Shared | I26: Frontend | J26: Must | K26: MVP | L26: 5 | M26: 6 | N26: =IF(M26<=4,"R1 Foundation",IF(M26<=8,"R2 Core Clinic",IF(M26<=13,"R3 Revenue & Messaging",IF(M26<=18,"R4 Patient & Platform",IF(M26<=20,"R5 Harden","R6 Launch"))))) | O26: =L26*README!$B$32 | P26: NB-022 | Q26: Compaction correct for INR lakh and SAR conventions in all three languages | R26: Not started
A27: NB-026 | B27: E03 Chart & Data-Visualisation System | C27: Charts | D27: Legend, direct labels, tooltip & crosshair | E27: Reuses the 8.9 tooltip surface. Labels never wear the series colour; a label that will not fit moves or drops to the tooltip, never clips. | G27: All | H27: Shared | I27: Frontend | J27: Must | K27: MVP | L27: 5 | M27: 7 | N27: =IF(M27<=4,"R1 Foundation",IF(M27<=8,"R2 Core Clinic",IF(M27<=13,"R3 Revenue & Messaging",IF(M27<=18,"R4 Patient & Platform",IF(M27<=20,"R5 Harden","R6 Launch"))))) | O27: =L27*README!$B$32 | P27: NB-024 | Q27: No clipped label at any breakpoint; single-series charts render no legend | R27: Not started
A28: NB-027 | B28: E03 Chart & Data-Visualisation System | C28: Charts | D28: Mandatory table view & export path for every chart | E28: Every chart ships a table view — the sub-3:1 relief channel, the screen-reader equivalent and the export path. | F28: SYS-23 | G28: All | H28: Shared | I28: Frontend | J28: Must | K28: MVP | L28: 5 | M28: 7 | N28: =IF(M28<=4,"R1 Foundation",IF(M28<=8,"R2 Core Clinic",IF(M28<=13,"R3 Revenue & Messaging",IF(M28<=18,"R4 Patient & Platform",IF(M28<=20,"R5 Harden","R6 Launch"))))) | O28: =L28*README!$B$32 | P28: NB-024 | Q28: No chart ships without a table view; screen reader reads the table, not the SVG | R28: Not started
A29: NB-028 | B29: E03 Chart & Data-Visualisation System | C29: Charts | D29: Ten chart states | E29: Empty with reason, single data point, insufficient data, loading, offline/stale, partial data (gaps stay gaps), unit-ambiguous, threshold band, permission-restricted, subscription-unavailable. | F29: PED-03,GP-03 | G29: All | H29: Shared | I29: Frontend | J29: Must | K29: MVP | L29: 8 | M29: 8 | N29: =IF(M29<=4,"R1 Foundation",IF(M29<=8,"R2 Core Clinic",IF(M29<=13,"R3 Revenue & Messaging",IF(M29<=18,"R4 Patient & Platform",IF(M29<=20,"R5 Harden","R6 Launch"))))) | O29: =L29*README!$B$32 | P29: NB-024, NB-020 | Q29: All ten states demonstrated; a one-point trend degrades to a stat tile rather than erroring | R29: Not started
A30: NB-029 | B30: E03 Chart & Data-Visualisation System | C30: Charts | D30: Chart RTL & aggregation rules | E30: Time axes never mirror; category axes and legends do. Charts past ~200 marks aggregate before rendering and say so. | F30: NFR-02 | G30: All | H30: Shared | I30: Frontend | J30: Must | K30: MVP | L30: 5 | M30: 9 | N30: =IF(M30<=4,"R1 Foundation",IF(M30<=8,"R2 Core Clinic",IF(M30<=13,"R3 Revenue & Messaging",IF(M30<=18,"R4 Patient & Platform",IF(M30<=20,"R5 Harden","R6 Launch"))))) | O30: =L30*README!$B$32 | P30: NB-024, NB-031 | Q30: Arabic time-axis chart verified unmirrored; 500-mark dataset aggregates with a visible notice | R30: Not started
A31: NB-030 | B31: E04 Localisation, RTL & i18n | C31: i18n | D31: i18n framework & string extraction pipeline | E31: EN / AR / HI bundles plus the patient-side language set (Hinglish, Tamil, Malayalam, Kannada, Bengali). No hardcoded strings. | F31: PAT-15 | G31: All | H31: Shared | I31: Frontend | J31: Must | K31: MVP | L31: 8 | M31: 3 | N31: =IF(M31<=4,"R1 Foundation",IF(M31<=8,"R2 Core Clinic",IF(M31<=13,"R3 Revenue & Messaging",IF(M31<=18,"R4 Patient & Platform",IF(M31<=20,"R5 Harden","R6 Launch"))))) | O31: =L31*README!$B$32 | P31: NB-017 | Q31: Lint fails on literal UI strings; pseudo-locale build available | R31: Not started
A32: NB-031 | B32: E04 Localisation, RTL & i18n | C32: i18n | D32: RTL layout engine — logical properties only | E32: No left/right in shipped CSS. Nav, drawer, table order, chevrons and selected bar all mirror. | G32: All | H32: Shared | I32: Frontend | J32: Must | K32: MVP | L32: 8 | M32: 4 | N32: =IF(M32<=4,"R1 Foundation",IF(M32<=8,"R2 Core Clinic",IF(M32<=13,"R3 Revenue & Messaging",IF(M32<=18,"R4 Patient & Platform",IF(M32<=20,"R5 Harden","R6 Launch"))))) | O32: =L32*README!$B$32 | P32: NB-030, NB-017 | Q32: Stylelint blocks physical properties; RTL screenshot suite passes | R32: Not started
A33: NB-032 | B33: E04 Localisation, RTL & i18n | C33: i18n | D33: RTL non-mirroring exception list including anatomy | E33: Clock glyphs, media, pulse mark, all time axes, phone numbers, Latin IDs, illustrations — and anatomy: the dental arch and dermatology body map keep fixed LTR order with both ends labelled. | F33: DENT-01,DERM-04 | G33: All | H33: Shared | I33: Frontend | J33: Must | K33: MVP | L33: 5 | M33: 5 | N33: =IF(M33<=4,"R1 Foundation",IF(M33<=8,"R2 Core Clinic",IF(M33<=13,"R3 Revenue & Messaging",IF(M33<=18,"R4 Patient & Platform",IF(M33<=20,"R5 Harden","R6 Launch"))))) | O33: =L33*README!$B$32 | P33: NB-031 | Q33: Dental arch and body map verified unmirrored in Arabic with explicit end labels | R33: Not started
A34: NB-033 | B34: E04 Localisation, RTL & i18n | C34: i18n | D34: Arabic & Devanagari typography | E34: IBM Plex Sans Arabic pairing, line-height +0.1em, letter-spacing forced to zero. | G34: All | H34: Shared | I34: Frontend | J34: Must | K34: MVP | L34: 3 | M34: 4 | N34: =IF(M34<=4,"R1 Foundation",IF(M34<=8,"R2 Core Clinic",IF(M34<=13,"R3 Revenue & Messaging",IF(M34<=18,"R4 Patient & Platform",IF(M34<=20,"R5 Harden","R6 Launch"))))) | O34: =L34*README!$B$32 | P34: NB-030 | Q34: Arabic renders untracked; no clipped descenders | R34: Not started
A35: NB-034 | B35: E04 Localisation, RTL & i18n | C35: i18n | D35: Hijri + Gregorian dual calendar | E35: KSA tenants show Hijri primary with Gregorian secondary on one line; India Gregorian only. | G35: Reception,Doctor,Owner | H35: Shared | I35: Frontend | J35: Must | K35: MVP | L35: 5 | M35: 5 | N35: =IF(M35<=4,"R1 Foundation",IF(M35<=8,"R2 Core Clinic",IF(M35<=13,"R3 Revenue & Messaging",IF(M35<=18,"R4 Patient & Platform",IF(M35<=20,"R5 Harden","R6 Launch"))))) | O35: =L35*README!$B$32 | P35: NB-030 | Q35: Date component unit-tested across both regions and month boundaries | R35: Not started
A36: NB-035 | B36: E04 Localisation, RTL & i18n | C36: i18n | D36: Number, currency & numeral configuration | E36: Western digits by default for clinical and financial values; INR en-IN grouping vs SAR trailing symbol. Arabic-Indic tenant-configurable. | G36: Reception,Owner | H36: Shared | I36: Frontend | J36: Must | K36: MVP | L36: 3 | M36: 5 | N36: =IF(M36<=4,"R1 Foundation",IF(M36<=8,"R2 Core Clinic",IF(M36<=13,"R3 Revenue & Messaging",IF(M36<=18,"R4 Patient & Platform",IF(M36<=20,"R5 Harden","R6 Launch"))))) | O36: =L36*README!$B$32 | P36: NB-030 | Q36: Currency formatting matches the wireframe for both regions | R36: Not started
A37: NB-036 | B37: E04 Localisation, RTL & i18n | C37: i18n | D37: Ramadan & prayer-time schedule mode | E37: Prayer breaks and Ramadan hours change slot generation for KSA tenants. | F37: SYS-04,CAD-05 | G37: Reception,Doctor | H37: Clinic | I37: Fullstack | J37: Must | K37: MVP | L37: 5 | M37: 8 | N37: =IF(M37<=4,"R1 Foundation",IF(M37<=8,"R2 Core Clinic",IF(M37<=13,"R3 Revenue & Messaging",IF(M37<=18,"R4 Patient & Platform",IF(M37<=20,"R5 Harden","R6 Launch"))))) | O37: =L37*README!$B$32 | P37: NB-090 | Q37: Prayer blocks appear as non-bookable; Ramadan toggle shifts the whole day template | R37: Not started
A38: NB-037 | B38: E04 Localisation, RTL & i18n | C38: i18n | D38: String-expansion resilience pass | E38: ~30% expansion in Hindi and Arabic; every label container wraps, none truncate below two lines. | G38: All | H38: Shared | I38: Frontend | J38: Should | K38: MVP | L38: 3 | M38: 7 | N38: =IF(M38<=4,"R1 Foundation",IF(M38<=8,"R2 Core Clinic",IF(M38<=13,"R3 Revenue & Messaging",IF(M38<=18,"R4 Patient & Platform",IF(M38<=20,"R5 Harden","R6 Launch"))))) | O38: =L38*README!$B$32 | P38: NB-030 | Q38: Pseudo-locale run shows zero truncation defects | R38: Not started
A39: NB-038 | B39: E04 Localisation, RTL & i18n | C39: i18n | D39: Clinical & regulatory terminology review | E39: Native clinician review of Arabic and Hindi clinical strings. Mistranslation here is a patient-safety risk. | G39: Doctor,Nurse | H39: Shared | I39: QA | J39: Must | K39: MVP | L39: 5 | M39: 16 | N39: =IF(M39<=4,"R1 Foundation",IF(M39<=8,"R2 Core Clinic",IF(M39<=13,"R3 Revenue & Messaging",IF(M39<=18,"R4 Patient & Platform",IF(M39<=20,"R5 Harden","R6 Launch"))))) | O39: =L39*README!$B$32 | P39: NB-030, NB-103 | Q39: Sign-off from a licensed reviewer per language | R39: Not started
A40: NB-039 | B40: E04 Localisation, RTL & i18n | C40: i18n | D40: Voice-note handling on the patient channel | E40: Patients send voice notes; the clinic receives them transcribed or playable without leaving the inbox. | F40: PAT-15 | G40: Patient,Reception | H40: Patient | I40: Fullstack | J40: Should | K40: Phase 2 | L40: 8 | M40: 17 | N40: =IF(M40<=4,"R1 Foundation",IF(M40<=8,"R2 Core Clinic",IF(M40<=13,"R3 Revenue & Messaging",IF(M40<=18,"R4 Patient & Platform",IF(M40<=20,"R5 Harden","R6 Launch"))))) | O40: =L40*README!$B$32 | P40: NB-197, NB-030 | Q40: Voice note playable in the shared inbox; transcription failure degrades gracefully to audio | R40: Not started
A41: NB-040 | B41: E05 Identity, Auth & Session | C41: Auth | D41: Staff authentication — WhatsApp OTP, short PIN, authenticator app | E41: The three supported methods. NFR-06 explicitly rules out SSO and hardware security keys — do not build them. | F41: NFR-06,SYS-01 | G41: All | H41: Shared | I41: Security | J41: Must | K41: MVP | L41: 8 | M41: 2 | N41: =IF(M41<=4,"R1 Foundation",IF(M41<=8,"R2 Core Clinic",IF(M41<=13,"R3 Revenue & Messaging",IF(M41<=18,"R4 Patient & Platform",IF(M41<=20,"R5 Harden","R6 Launch"))))) | O41: =L41*README!$B$32 | P41: NB-001, NB-003 | Q41: All three methods work; no SSO or WebAuthn code path exists; OWASP ASVS L2 auth controls verified | R41: Done
A42: NB-041 | B42: E05 Identity, Auth & Session | C42: Auth | D42: Dual-channel staff identity — verified email + mobile | E42: Mobile receives the WhatsApp OTP, email receives the activation link. Both are required before any patient data is reachable. | F42: CAD-12 | G42: All | H42: Shared | I42: Security | J42: Must | K42: MVP | L42: 5 | M42: 3 | N42: =IF(M42<=4,"R1 Foundation",IF(M42<=8,"R2 Core Clinic",IF(M42<=13,"R3 Revenue & Messaging",IF(M42<=18,"R4 Patient & Platform",IF(M42<=20,"R5 Harden","R6 Launch"))))) | O42: =L42*README!$B$32 | P42: NB-040 | Q42: Access to patient data is impossible until both channels are verified | R42: Done
A43: NB-042 | B43: E05 Identity, Auth & Session | C43: Auth | D43: Authenticator-app MFA enforcement | E43: Mandatory for Owner, Platform operators and anyone holding refund or discount rights. | F43: NFR-06 | G43: Owner,Platform | H43: Shared | I43: Security | J43: Must | K43: MVP | L43: 5 | M43: 4 | N43: =IF(M43<=4,"R1 Foundation",IF(M43<=8,"R2 Core Clinic",IF(M43<=13,"R3 Revenue & Messaging",IF(M43<=18,"R4 Patient & Platform",IF(M43<=20,"R5 Harden","R6 Launch"))))) | O43: =L43*README!$B$32 | P43: NB-040 | Q43: MFA enforced by policy; recovery codes single-use | R43: Done
A44: NB-043 | B44: E05 Identity, Auth & Session | C44: Auth | D44: Session management & device trust | E44: Short-lived access token, rotating refresh, per-device session list, remote revoke. | G44: All | H44: Shared | I44: Security | J44: Must | K44: MVP | L44: 5 | M44: 3 | N44: =IF(M44<=4,"R1 Foundation",IF(M44<=8,"R2 Core Clinic",IF(M44<=13,"R3 Revenue & Messaging",IF(M44<=18,"R4 Patient & Platform",IF(M44<=20,"R5 Harden","R6 Launch"))))) | O44: =L44*README!$B$32 | P44: NB-040 | Q44: Revoked session denied within 60s; refresh-token reuse detected | R44: Done
A45: NB-044 | B45: E05 Identity, Auth & Session | C45: Auth | D45: Idle timeout & clinical screen lock | E45: Shared clinic workstations auto-lock with fast re-auth and no loss of draft clinical notes. | G45: Reception,Nurse,Doctor | H45: Clinic | I45: Frontend | J45: Must | K45: MVP | L45: 3 | M45: 6 | N45: =IF(M45<=4,"R1 Foundation",IF(M45<=8,"R2 Core Clinic",IF(M45<=13,"R3 Revenue & Messaging",IF(M45<=18,"R4 Patient & Platform",IF(M45<=20,"R5 Harden","R6 Launch"))))) | O45: =L45*README!$B$32 | P45: NB-043 | Q45: Draft consultation notes survive lock and unlock | R45: Done
A46: NB-045 | B46: E05 Identity, Auth & Session | C46: Auth | D46: Staff invite, onboarding & first sign-in | E46: Matches the Invited / Pending first sign-in state in the Staff wireframe. | F46: CAD-12 | G46: Owner | H46: Clinic | I46: Fullstack | J46: Must | K46: MVP | L46: 5 | M46: 7 | N46: =IF(M46<=4,"R1 Foundation",IF(M46<=8,"R2 Core Clinic",IF(M46<=13,"R3 Revenue & Messaging",IF(M46<=18,"R4 Patient & Platform",IF(M46<=20,"R5 Harden","R6 Launch"))))) | O46: =L46*README!$B$32 | P46: NB-041, NB-049 | Q46: Invite expires in 72h, single use, audited | R46: Done
A47: NB-046 | B47: E05 Identity, Auth & Session | C47: Auth | D47: Password/PIN reset & account recovery | E47: Rate-limited, token-based, no user enumeration. | G47: All | H47: Shared | I47: Security | J47: Must | K47: MVP | L47: 3 | M47: 5 | N47: =IF(M47<=4,"R1 Foundation",IF(M47<=8,"R2 Core Clinic",IF(M47<=13,"R3 Revenue & Messaging",IF(M47<=18,"R4 Patient & Platform",IF(M47<=20,"R5 Harden","R6 Launch"))))) | O47: =L47*README!$B$32 | P47: NB-040 | Q47: Timing and copy identical for known and unknown accounts | R47: Done
A48: NB-047 | B48: E05 Identity, Auth & Session | C48: Auth | D48: Staff suspension & immediate session termination | E48: A suspended staff member loses access on every device at once. | G48: Owner | H48: Clinic | I48: Backend | J48: Must | K48: MVP | L48: 3 | M48: 7 | N48: =IF(M48<=4,"R1 Foundation",IF(M48<=8,"R2 Core Clinic",IF(M48<=13,"R3 Revenue & Messaging",IF(M48<=18,"R4 Patient & Platform",IF(M48<=20,"R5 Harden","R6 Launch"))))) | O48: =L48*README!$B$32 | P48: NB-043, NB-045 | Q48: Suspension kills live sessions within 30s and writes an audit event | R48: Done
A49: NB-048 | B49: E05 Identity, Auth & Session | C49: Auth | D49: Break-glass emergency access | E49: Time-boxed elevated access with mandatory reason and loud audit alerting. | F49: SYS-13 | G49: Doctor,Owner | H49: Clinic | I49: Security | J49: Should | K49: Phase 2 | L49: 5 | M49: 15 | N49: =IF(M49<=4,"R1 Foundation",IF(M49<=8,"R2 Core Clinic",IF(M49<=13,"R3 Revenue & Messaging",IF(M49<=18,"R4 Patient & Platform",IF(M49<=20,"R5 Harden","R6 Launch"))))) | O49: =L49*README!$B$32 | P49: NB-049, NB-238 | Q49: Break-glass expires automatically; owner notified in real time | R49: Done
A50: NB-049 | B50: E06 RBAC & Permissions | C50: RBAC | D50: Clinic role & permission model (10 modules x 7 actions) | E50: Patients, Queue, Clinical, Billing, Packages, Pharmacy, Reports, Staff & Access, Setup, Compliance across Owner / Doctor / Reception / Nurse / Custom. | G50: All | H50: Clinic | I50: Backend | J50: Must | K50: MVP | L50: 8 | M50: 4 | N50: =IF(M50<=4,"R1 Foundation",IF(M50<=8,"R2 Core Clinic",IF(M50<=13,"R3 Revenue & Messaging",IF(M50<=18,"R4 Patient & Platform",IF(M50<=20,"R5 Harden","R6 Launch"))))) | O50: =L50*README!$B$32 | P50: NB-003 | Q50: Matrix matches the wireframe PERMS fixture exactly; unit-tested per role | R50: Done
A51: NB-050 | B51: E06 RBAC & Permissions | C51: RBAC | D51: Server-side policy enforcement point | E51: Deny by default on every endpoint. No client-only gating anywhere. | G51: All | H51: Shared | I51: Security | J51: Must | K51: MVP | L51: 8 | M51: 5 | N51: =IF(M51<=4,"R1 Foundation",IF(M51<=8,"R2 Core Clinic",IF(M51<=13,"R3 Revenue & Messaging",IF(M51<=18,"R4 Patient & Platform",IF(M51<=20,"R5 Harden","R6 Launch"))))) | O51: =L51*README!$B$32 | P51: NB-049, NB-040 | Q51: Automated test asserts 403 for every role/endpoint pair not granted | R51: Done
A52: NB-051 | B52: E06 RBAC & Permissions | C52: RBAC | D52: Row-level scoping — own patients vs all clinic patients | E52: Enforced in the query, not by post-filtering. | G52: Doctor | H52: Clinic | I52: Backend | J52: Must | K52: MVP | L52: 8 | M52: 6 | N52: =IF(M52<=4,"R1 Foundation",IF(M52<=8,"R2 Core Clinic",IF(M52<=13,"R3 Revenue & Messaging",IF(M52<=18,"R4 Patient & Platform",IF(M52<=20,"R5 Harden","R6 Launch"))))) | O52: =L52*README!$B$32 | P52: NB-050 | Q52: Direct-ID access to another doctor's patient returns 404, not 403 | R52: Done
A53: NB-052 | B53: E06 RBAC & Permissions | C53: RBAC | D53: Field-level restrictions | E53: No financial fields, no refund, no discount, vitals-and-vaccines-only custom grants. | G53: Reception,Nurse | H53: Clinic | I53: Backend | J53: Must | K53: MVP | L53: 5 | M53: 6 | N53: =IF(M53<=4,"R1 Foundation",IF(M53<=8,"R2 Core Clinic",IF(M53<=13,"R3 Revenue & Messaging",IF(M53<=18,"R4 Patient & Platform",IF(M53<=20,"R5 Harden","R6 Launch"))))) | O53: =L53*README!$B$32 | P53: NB-050 | Q53: Restricted fields are absent from the API response, not merely hidden | R53: Done
A54: NB-053 | B54: E06 RBAC & Permissions | C54: RBAC | D54: Consent checked at query level | E54: Consent state is evaluated in the data access path, not in the UI — a withdrawn consent removes the data from results. | F54: NFR-08,CMP-02 | G54: All | H54: Shared | I54: Backend | J54: Must | K54: MVP | L54: 8 | M54: 7 | N54: =IF(M54<=4,"R1 Foundation",IF(M54<=8,"R2 Core Clinic",IF(M54<=13,"R3 Revenue & Messaging",IF(M54<=18,"R4 Patient & Platform",IF(M54<=20,"R5 Harden","R6 Launch"))))) | O54: =L54*README!$B$32 | P54: NB-050, NB-003 | Q54: Query-level consent check demonstrated; bypassing the UI does not expose consent-gated data | R54: Done
A55: NB-054 | B55: E06 RBAC & Permissions | C55: RBAC | D55: UI permission rendering contract | E55: Permission-restricted elements are absent, never disabled or greyed. | F55: SSA-02 | G55: All | H55: Shared | I55: Frontend | J55: Must | K55: MVP | L55: 5 | M55: 6 | N55: =IF(M55<=4,"R1 Foundation",IF(M55<=8,"R2 Core Clinic",IF(M55<=13,"R3 Revenue & Messaging",IF(M55<=18,"R4 Patient & Platform",IF(M55<=20,"R5 Harden","R6 Launch"))))) | O55: =L55*README!$B$32 | P55: NB-050, NB-013 | Q55: Automated DOM assertion: no disabled element carries a permission reason; no create button exists for roles without create rights | R55: Done
A56: NB-055 | B56: E06 RBAC & Permissions | C56: RBAC | D56: Custom role builder & permission matrix UI | E56: Owner-facing 640px matrix modal for bespoke roles. | G56: Owner | H56: Clinic | I56: Frontend | J56: Should | K56: MVP | L56: 8 | M56: 9 | N56: =IF(M56<=4,"R1 Foundation",IF(M56<=8,"R2 Core Clinic",IF(M56<=13,"R3 Revenue & Messaging",IF(M56<=18,"R4 Patient & Platform",IF(M56<=20,"R5 Harden","R6 Launch"))))) | O56: =L56*README!$B$32 | P56: NB-049 | Q56: Owner can reproduce the wireframe's Front Desk + Vitals role | R56: Done
A57: NB-056 | B57: E06 RBAC & Permissions | C57: RBAC | D57: Approval workflows & maker-checker | E57: Refunds, discounts above threshold, clinical amendments and platform discount approvals all need a second approver. | F57: SYS-06 | G57: Owner,Reception | H57: Shared | I57: Fullstack | J57: Must | K57: MVP | L57: 8 | M57: 10 | N57: =IF(M57<=4,"R1 Foundation",IF(M57<=8,"R2 Core Clinic",IF(M57<=13,"R3 Revenue & Messaging",IF(M57<=18,"R4 Patient & Platform",IF(M57<=20,"R5 Harden","R6 Launch"))))) | O57: =L57*README!$B$32 | P57: NB-050, NB-238 | Q57: Self-approval blocked; approval chain visible in the audit log | R57: Done
A58: NB-057 | B58: E06 RBAC & Permissions | C58: RBAC | D58: Delegation & temporary access grants | E58: Cover a doctor's leave without permanently widening rights; auto-expiring. | G58: Owner | H58: Clinic | I58: Backend | J58: Could | K58: Phase 2 | L58: 5 | M58: 18 | N58: =IF(M58<=4,"R1 Foundation",IF(M58<=8,"R2 Core Clinic",IF(M58<=13,"R3 Revenue & Messaging",IF(M58<=18,"R4 Patient & Platform",IF(M58<=20,"R5 Harden","R6 Launch"))))) | O58: =L58*README!$B$32 | P58: NB-049 | Q58: Grant expires on schedule and the expiry is audited | R58: Done
A59: NB-058 | B59: E06 RBAC & Permissions | C59: RBAC | D59: Subscription vs permission state separation | E59: Subscription-unavailable modules appear only in Catalog/Plan/Setup with historical data still readable; permission-restricted ones vanish entirely. | F59: DENT-06,DENT-07,DERM-04,DERM-07 | G59: All | H59: Shared | I59: Frontend | J59: Must | K59: MVP | L59: 5 | M59: 9 | N59: =IF(M59<=4,"R1 Foundation",IF(M59<=8,"R2 Core Clinic",IF(M59<=13,"R3 Revenue & Messaging",IF(M59<=18,"R4 Patient & Platform",IF(M59<=20,"R5 Harden","R6 Launch"))))) | O59: =L59*README!$B$32 | P59: NB-008, NB-054 | Q59: Both states verified; ending a trial leaves historical data readable | R59: Not started
A60: NB-059 | B60: E06 RBAC & Permissions | C60: RBAC | D60: Staff & Access screen | E60: Staff list, status, scope summary, last-seen and role chips. | G60: Owner | H60: Clinic | I60: Frontend | J60: Must | K60: MVP | L60: 5 | M60: 9 | N60: =IF(M60<=4,"R1 Foundation",IF(M60<=8,"R2 Core Clinic",IF(M60<=13,"R3 Revenue & Messaging",IF(M60<=18,"R4 Patient & Platform",IF(M60<=20,"R5 Harden","R6 Launch"))))) | O60: =L60*README!$B$32 | P60: NB-049, NB-045 | Q60: Screen matches the wireframe; every action permission-gated | R60: Done
A61: NB-060 | B61: E07 Clinic Setup & Administration | C61: Setup | D61: Guided clinic setup wizard — skippable and resumable | E61: Welcome, clinic profile, and the remaining steps. Every step can be skipped and resumed; fully self-serve with no support intervention. | F61: CAD-01,SYS-21,NFR-18 | G61: Owner | H61: Clinic | I61: Fullstack | J61: Must | K61: MVP | L61: 13 | M61: 7 | N61: =IF(M61<=4,"R1 Foundation",IF(M61<=8,"R2 Core Clinic",IF(M61<=13,"R3 Revenue & Messaging",IF(M61<=18,"R4 Patient & Platform",IF(M61<=20,"R5 Harden","R6 Launch"))))) | O61: =L61*README!$B$32 | P61: NB-261, NB-017 | Q61: A new clinic goes live unaided; closing the wizard mid-way and returning resumes at the same step | R61: Done
A62: NB-061 | B62: E07 Clinic Setup & Administration | C62: Setup | D62: Charge head / price master management | E62: Effective-dated service codes, categories, INR/SAR prices, GST/VAT rates, package eligibility and active flag. | F62: CAD-04 | G62: Owner | H62: Clinic | I62: Fullstack | J62: Must | K62: MVP | L62: 8 | M62: 8 | N62: =IF(M62<=4,"R1 Foundation",IF(M62<=8,"R2 Core Clinic",IF(M62<=13,"R3 Revenue & Messaging",IF(M62<=18,"R4 Patient & Platform",IF(M62<=20,"R5 Harden","R6 Launch"))))) | O62: =L62*README!$B$32 | P62: NB-010 | Q62: Reproduces the wireframe's 24 charge heads with effective-dated pricing | R62: Done
A63: NB-062 | B63: E07 Clinic Setup & Administration | C63: Setup | D63: Simple policy settings | E63: Clinic-level operational policies exposed as plain settings, not a rules engine. | F63: CAD-06 | G63: Owner | H63: Clinic | I63: Fullstack | J63: Must | K63: MVP | L63: 5 | M63: 10 | N63: =IF(M63<=4,"R1 Foundation",IF(M63<=8,"R2 Core Clinic",IF(M63<=13,"R3 Revenue & Messaging",IF(M63<=18,"R4 Patient & Platform",IF(M63<=20,"R5 Harden","R6 Launch"))))) | O63: =L63*README!$B$32 | P63: NB-060 | Q63: Policy changes take effect without a redeploy and are audited | R63: Done
A64: NB-063 | B64: E07 Clinic Setup & Administration | C64: Setup | D64: Consent & privacy notice contact settings | E64: Contact details only — the template library itself lives in Compliance & Audit. | F64: CAD-08 | G64: Owner | H64: Clinic | I64: Frontend | J64: Must | K64: MVP | L64: 3 | M64: 11 | N64: =IF(M64<=4,"R1 Foundation",IF(M64<=8,"R2 Core Clinic",IF(M64<=13,"R3 Revenue & Messaging",IF(M64<=18,"R4 Patient & Platform",IF(M64<=20,"R5 Harden","R6 Launch"))))) | O64: =L64*README!$B$32 | P64: NB-240 | Q64: Only contact fields are editable here; the library is reachable but not duplicated | R64: Done
A65: NB-064 | B65: E07 Clinic Setup & Administration | C65: Setup | D65: Clinic schedule & calendar administration | E65: Working hours, visit-type durations, holidays and clinic-wide calendar rules. | F65: CAD-05 | G65: Owner | H65: Clinic | I65: Fullstack | J65: Must | K65: MVP | L65: 8 | M65: 8 | N65: =IF(M65<=4,"R1 Foundation",IF(M65<=8,"R2 Core Clinic",IF(M65<=13,"R3 Revenue & Messaging",IF(M65<=18,"R4 Patient & Platform",IF(M65<=20,"R5 Harden","R6 Launch"))))) | O65: =L65*README!$B$32 | P65: NB-060 | Q65: Visit-type durations drive slot generation; holidays block booking | R65: Done
A66: NB-065 | B66: E07 Clinic Setup & Administration | C66: Setup | D66: Shift timings & attendance | E66: Staff shift patterns and attendance capture. | F66: CAD-09 | G66: Owner | H66: Clinic | I66: Fullstack | J66: Could | K66: Phase 2 | L66: 8 | M66: 19 | N66: =IF(M66<=4,"R1 Foundation",IF(M66<=8,"R2 Core Clinic",IF(M66<=13,"R3 Revenue & Messaging",IF(M66<=18,"R4 Patient & Platform",IF(M66<=20,"R5 Harden","R6 Launch"))))) | O66: =L66*README!$B$32 | P66: NB-092 | Q66: Shift roster drives the payroll export; attendance editable with audit | R66: Done
A67: NB-066 | B67: E07 Clinic Setup & Administration | C67: Setup | D67: Simple payroll export | E67: CSV of days, hours, salary and notes with optional PF/ESI columns. There is deliberately no payroll engine. | F67: CAD-10 | G67: Owner | H67: Clinic | I67: Fullstack | J67: Should | K67: MVP | L67: 5 | M67: 17 | N67: =IF(M67<=4,"R1 Foundation",IF(M67<=8,"R2 Core Clinic",IF(M67<=13,"R3 Revenue & Messaging",IF(M67<=18,"R4 Patient & Platform",IF(M67<=20,"R5 Harden","R6 Launch"))))) | O67: =L67*README!$B$32 | P67: NB-092 | Q67: CSV opens in Excel without cleanup; no calculation engine is built | R67: Done
A68: NB-067 | B68: E07 Clinic Setup & Administration | C68: Setup | D68: Tenant subscription & plan self-service | E68: Current plan, usage against limits, and upgrade or downgrade taking effect in under five minutes with no data loss. | F68: CAD-13,SYS-20 | G68: Owner | H68: Clinic | I68: Fullstack | J68: Should | K68: Phase 3 | L68: 8 | M68: 20 | N68: =IF(M68<=4,"R1 Foundation",IF(M68<=8,"R2 Core Clinic",IF(M68<=13,"R3 Revenue & Messaging",IF(M68<=18,"R4 Patient & Platform",IF(M68<=20,"R5 Harden","R6 Launch"))))) | O68: =L68*README!$B$32 | P68: NB-008, NB-269 | Q68: Plan change completes under 5 minutes; no data is lost in either direction | R68: Done
A69: NB-068 | B69: E07 Clinic Setup & Administration | C69: Setup | D69: Self-serve data import & export | E69: Import wizard and full export without support involvement. | F69: SYS-23,NFR-18 | G69: Owner | H69: Clinic | I69: Fullstack | J69: Must | K69: MVP | L69: 8 | M69: 15 | N69: =IF(M69<=4,"R1 Foundation",IF(M69<=8,"R2 Core Clinic",IF(M69<=13,"R3 Revenue & Messaging",IF(M69<=18,"R4 Patient & Platform",IF(M69<=20,"R5 Harden","R6 Launch"))))) | O69: =L69*README!$B$32 | P69: NB-003, NB-071 | Q69: Import dry-runs before writing; export completes unaided | R69: Done
A70: NB-069 | B70: E07 Clinic Setup & Administration | C70: Setup | D70: Setup completeness checklist | E70: The clinic sees what is still outstanding — price master, WhatsApp number, screen pairing — with a direct route to each. | F70: CAD-01,RCP-14,CAD-07 | G70: Owner | H70: Clinic | I70: Frontend | J70: Should | K70: MVP | L70: 3 | M70: 12 | N70: =IF(M70<=4,"R1 Foundation",IF(M70<=8,"R2 Core Clinic",IF(M70<=13,"R3 Revenue & Messaging",IF(M70<=18,"R4 Patient & Platform",IF(M70<=20,"R5 Harden","R6 Launch"))))) | O70: =L70*README!$B$32 | P70: NB-060 | Q70: Checklist state derives from real configuration, never a manual tick | R70: Done
A71: NB-070 | B71: E07 Clinic Setup & Administration | C71: Setup | D71: Facility & licence registry | E71: Clinic facility record, licence numbers and registration identifiers used on invoices and claim packs. | F71: CMP-11,BIL-11 | G71: Owner | H71: Clinic | I71: Backend | J71: Must | K71: MVP | L71: 5 | M71: 11 | N71: =IF(M71<=4,"R1 Foundation",IF(M71<=8,"R2 Core Clinic",IF(M71<=13,"R3 Revenue & Messaging",IF(M71<=18,"R4 Patient & Platform",IF(M71<=20,"R5 Harden","R6 Launch"))))) | O71: =L71*README!$B$32 | P71: NB-060 | Q71: Licence number is available to the claim pack and invoice generators | R71: Done
A72: NB-071 | B72: E08 Patient Records & Registration | C72: Patients | D72: Patient registration & demographics | E72: Multi-script names, phone, DOB, gender, guardian, address and national ID (Aadhaar / Iqama) handling. | F72: PAT-01 | G72: Reception | H72: Clinic | I72: Fullstack | J72: Must | K72: MVP | L72: 8 | M72: 6 | N72: =IF(M72<=4,"R1 Foundation",IF(M72<=8,"R2 Core Clinic",IF(M72<=13,"R3 Revenue & Messaging",IF(M72<=18,"R4 Patient & Platform",IF(M72<=20,"R5 Harden","R6 Launch"))))) | O72: =L72*README!$B$32 | P72: NB-003, NB-013 | Q72: Arabic and Devanagari names store, search and print correctly | R72: Done
A73: NB-072 | B73: E08 Patient Records & Registration | C73: Patients | D73: Duplicate detection & supervised merge | E73: Fuzzy match on registration; merge preserves every encounter and invoice and is reversible. | G73: Reception,Owner | H73: Clinic | I73: Backend | J73: Must | K73: MVP | L73: 8 | M73: 11 | N73: =IF(M73<=4,"R1 Foundation",IF(M73<=8,"R2 Core Clinic",IF(M73<=13,"R3 Revenue & Messaging",IF(M73<=18,"R4 Patient & Platform",IF(M73<=20,"R5 Harden","R6 Launch"))))) | O73: =L73*README!$B$32 | P73: NB-071 | Q73: Merge is reversible for 30 days and fully audited | R73: Done
A74: NB-073 | B74: E08 Patient Records & Registration | C74: Patients | D74: Patient search & directory | E74: Fast search by phone, name, token or MRN across scripts, scoped by role. | G74: Reception,Doctor,Nurse | H74: Clinic | I74: Fullstack | J74: Must | K74: MVP | L74: 5 | M74: 7 | N74: =IF(M74<=4,"R1 Foundation",IF(M74<=8,"R2 Core Clinic",IF(M74<=13,"R3 Revenue & Messaging",IF(M74<=18,"R4 Patient & Platform",IF(M74<=20,"R5 Harden","R6 Launch"))))) | O74: =L74*README!$B$32 | P74: NB-071 | Q74: p95 search under 300ms on 200k patients | R74: Done
A75: NB-074 | B75: E08 Patient Records & Registration | C75: Patients | D75: Patient 360 context drawer | E75: Identity, allergies, chronic conditions, active packages, outstanding balance, last visit. | F75: GP-02 | G75: Doctor,Nurse,Reception | H75: Clinic | I75: Frontend | J75: Must | K75: MVP | L75: 8 | M75: 9 | N75: =IF(M75<=4,"R1 Foundation",IF(M75<=8,"R2 Core Clinic",IF(M75<=13,"R3 Revenue & Messaging",IF(M75<=18,"R4 Patient & Platform",IF(M75<=20,"R5 Harden","R6 Launch"))))) | O75: =L75*README!$B$32 | P75: NB-071, NB-051 | Q75: Opens under 500ms; allergy banner always visible | R75: Done
A76: NB-075 | B76: E08 Patient Records & Registration | C76: Patients | D76: Patient document & report attachments | E76: Upload, virus scan, thumbnail and retention policy; feeds External Reports. | F76: SYS-18 | G76: Doctor,Nurse | H76: Clinic | I76: Fullstack | J76: Must | K76: MVP | L76: 5 | M76: 12 | N76: =IF(M76<=4,"R1 Foundation",IF(M76<=8,"R2 Core Clinic",IF(M76<=13,"R3 Revenue & Messaging",IF(M76<=18,"R4 Patient & Platform",IF(M76<=20,"R5 Harden","R6 Launch"))))) | O76: =L76*README!$B$32 | P76: NB-071, NB-292 | Q76: Malicious file rejected; files encrypted at rest with the tenant key | R76: Not started
A77: NB-076 | B77: E08 Patient Records & Registration | C77: Patients | D77: Secure file delivery via expiring link | E77: A file is never sent into an open chat. Delivery is always an expiring, access-logged link. | F77: SYS-18,PAT-13 | G77: Reception,Doctor,Patient | H77: Shared | I77: Backend | J77: Must | K77: MVP | L77: 5 | M77: 12 | N77: =IF(M77<=4,"R1 Foundation",IF(M77<=8,"R2 Core Clinic",IF(M77<=13,"R3 Revenue & Messaging",IF(M77<=18,"R4 Patient & Platform",IF(M77<=20,"R5 Harden","R6 Launch"))))) | O77: =L77*README!$B$32 | P77: NB-292 | Q77: No attachment is ever posted inline; link expires and every access is logged | R77: Not started
A78: NB-077 | B78: E08 Patient Records & Registration | C78: Patients | D78: Chronic condition & problem list | E78: Carried forward between encounters and driving chronic-review due lists. | F78: GP-02 | G78: Doctor | H78: Clinic | I78: Fullstack | J78: Must | K78: MVP | L78: 5 | M78: 12 | N78: =IF(M78<=4,"R1 Foundation",IF(M78<=8,"R2 Core Clinic",IF(M78<=13,"R3 Revenue & Messaging",IF(M78<=18,"R4 Patient & Platform",IF(M78<=20,"R5 Harden","R6 Launch"))))) | O78: =L78*README!$B$32 | P78: NB-071 | Q78: Chronic review due list is derived, not manually maintained | R78: Done
A79: NB-078 | B79: E08 Patient Records & Registration | C79: Patients | D79: Patient data export & erasure execution | E79: Subject-access export and erasure honouring clinical retention and legal hold. | F79: CMP-03,PAT-14,NFR-07 | G79: Owner | H79: Shared | I79: Backend | J79: Must | K79: MVP | L79: 5 | M79: 16 | N79: =IF(M79<=4,"R1 Foundation",IF(M79<=8,"R2 Core Clinic",IF(M79<=13,"R3 Revenue & Messaging",IF(M79<=18,"R4 Patient & Platform",IF(M79<=20,"R5 Harden","R6 Launch"))))) | O79: =L79*README!$B$32 | P79: NB-238, NB-071 | Q79: Export delivered within 72h as an expiring link; erasure respects statutory retention | R79: Not started
A80: NB-079 | B80: E08 Patient Records & Registration | C80: Patients | D80: Source tagging & attribution capture | E80: One source tag per visit, never a dual axis. Feeds the owner's where-patients-come-from view. | F80: OWN-02,MKT-04 | G80: Reception | H80: Clinic | I80: Backend | J80: Should | K80: MVP | L80: 3 | M80: 13 | N80: =IF(M80<=4,"R1 Foundation",IF(M80<=8,"R2 Core Clinic",IF(M80<=13,"R3 Revenue & Messaging",IF(M80<=18,"R4 Patient & Platform",IF(M80<=20,"R5 Harden","R6 Launch"))))) | O80: =L80*README!$B$32 | P80: NB-071 | Q80: Exactly one source tag per visit is enforced at write time | R80: Done
A81: NB-080 | B81: E09 Caregiver, Family & Guardianship | C81: Family | D81: One WhatsApp number, whole family | E81: A single member number shows no picker at all; multi-member numbers gain one. Booking stays within the six-tap budget. | F81: CGV-01,PAT-03 | G81: Patient | H81: Patient | I81: Fullstack | J81: Must | K81: MVP | L81: 8 | M81: 14 | N81: =IF(M81<=4,"R1 Foundation",IF(M81<=8,"R2 Core Clinic",IF(M81<=13,"R3 Revenue & Messaging",IF(M81<=18,"R4 Patient & Platform",IF(M81<=20,"R5 Harden","R6 Launch"))))) | O81: =L81*README!$B$32 | P81: NB-201, NB-071 | Q81: Single-member numbers never see a picker; booking completes in six taps or fewer | R81: Not started
A82: NB-081 | B82: E09 Caregiver, Family & Guardianship | C82: Family | D82: Add family member with consent capture | E82: Five-step in-chat flow ending in explicit consent for that member. | F82: CGV-02 | G82: Patient | H82: Patient | I82: Fullstack | J82: Must | K82: MVP | L82: 8 | M82: 14 | N82: =IF(M82<=4,"R1 Foundation",IF(M82<=8,"R2 Core Clinic",IF(M82<=13,"R3 Revenue & Messaging",IF(M82<=18,"R4 Patient & Platform",IF(M82<=20,"R5 Harden","R6 Launch"))))) | O82: =L82*README!$B$32 | P82: NB-080, NB-242 | Q82: Member cannot be added without recorded consent; each step is resumable | R82: Done
A83: NB-082 | B83: E09 Caregiver, Family & Guardianship | C83: Family | D83: Minor & guardian handling with age-18 handover | E83: Turning 18 automatically raises a guardian-access review task and moves consent to the patient. | F83: CGV-03,PED-06,CMP-04 | G83: Patient,Reception | H83: Patient | I83: Fullstack | J83: Must | K83: MVP | L83: 8 | M83: 15 | N83: =IF(M83<=4,"R1 Foundation",IF(M83<=8,"R2 Core Clinic",IF(M83<=13,"R3 Revenue & Messaging",IF(M83<=18,"R4 Patient & Platform",IF(M83<=20,"R5 Harden","R6 Launch"))))) | O83: =L83*README!$B$32 | P83: NB-081 | Q83: Age-18 transition fires automatically; consent stored separately per guardian | R83: Done
A84: NB-083 | B84: E09 Caregiver, Family & Guardianship | C84: Family | D84: Proxy booking, check-in & queue updates | E84: A caregiver books and checks in for another member; reminders always name the actual patient. | F84: CGV-04 | G84: Patient | H84: Patient | I84: Fullstack | J84: Must | K84: MVP | L84: 5 | M84: 15 | N84: =IF(M84<=4,"R1 Foundation",IF(M84<=8,"R2 Core Clinic",IF(M84<=13,"R3 Revenue & Messaging",IF(M84<=18,"R4 Patient & Platform",IF(M84<=20,"R5 Harden","R6 Launch"))))) | O84: =L84*README!$B$32 | P84: NB-080, NB-202 | Q84: Reminders name the patient, never the caregiver | R84: Not started
A85: NB-084 | B85: E09 Caregiver, Family & Guardianship | C85: Family | D85: Dual delivery of visit instructions | E85: Instructions reach both the patient and the nominated caregiver. | F85: CGV-05 | G85: Patient | H85: Patient | I85: Fullstack | J85: Should | K85: MVP | L85: 5 | M85: 16 | N85: =IF(M85<=4,"R1 Foundation",IF(M85<=8,"R2 Core Clinic",IF(M85<=13,"R3 Revenue & Messaging",IF(M85<=18,"R4 Patient & Platform",IF(M85<=20,"R5 Harden","R6 Launch"))))) | O85: =L85*README!$B$32 | P85: NB-083 | Q85: Both recipients receive the message; delivery state tracked per recipient | R85: Not started
A86: NB-085 | B86: E09 Caregiver, Family & Guardianship | C86: Family | D86: Proxy revocation & scope change | E86: A patient can revoke or narrow a caregiver's access at any time. | F86: CGV-06 | G86: Patient | H86: Patient | I86: Fullstack | J86: Must | K86: MVP | L86: 5 | M86: 16 | N86: =IF(M86<=4,"R1 Foundation",IF(M86<=8,"R2 Core Clinic",IF(M86<=13,"R3 Revenue & Messaging",IF(M86<=18,"R4 Patient & Platform",IF(M86<=20,"R5 Harden","R6 Launch"))))) | O86: =L86*README!$B$32 | P86: NB-081 | Q86: Revocation takes effect immediately across every surface and is audited | R86: Done
... A93: NB-092 | B93: E10 Queue, Scheduling & Availability | C93: Scheduling | D93: Roster, shifts, exceptions & holidays | E93: Weekly roster with per-day exceptions and clinic holidays. | F93: CAD-05,CAD-09 | G93: Owner | H93: Clinic | I93: Fullstack | J93: Must | K93: MVP | L93: 8 | M93: 10 | N93: =IF(M93<=4,"R1 Foundation",IF(M93<=8,"R2 Core Clinic",IF(M93<=13,"R3 Revenue & Messaging",IF(M93<=18,"R4 Patient & Platform",IF(M93<=20,"R5 Harden","R6 Launch"))))) | O93: =L93*README!$B$32 | P93: NB-064 | Q93: Exception overrides the roster for that date only | R93: Done
A94: NB-093 | B94: E10 Queue, Scheduling & Availability | C94: Queue | D94: Token & walk-in queue management | E94: Token issue, priority, reorder with mandatory reason and estimated wait. | G94: Reception | H94: Clinic | I94: Fullstack | J94: Must | K94: MVP | L94: 8 | M94: 8 | N94: =IF(M94<=4,"R1 Foundation",IF(M94<=8,"R2 Core Clinic",IF(M94<=13,"R3 Revenue & Messaging",IF(M94<=18,"R4 Patient & Platform",IF(M94<=20,"R5 Harden","R6 Launch"))))) | O94: =L94*README!$B$32 | P94: NB-090 | Q94: Token numbers unique per day per doctor; reorder audited | R94: Done
A95: NB-094 | B95: E10 Queue, Scheduling & Availability | C95: Queue | D95: Queue state machine | E95: Not arrived, checked in, waiting, vitals pending/done, in consultation, checkout pending, completed, no-show. | G95: Reception,Nurse,Doctor | H95: Clinic | I95: Backend | J95: Must | K95: MVP | L95: 5 | M95: 8 | N95: =IF(M95<=4,"R1 Foundation",IF(M95<=8,"R2 Core Clinic",IF(M95<=13,"R3 Revenue & Messaging",IF(M95<=18,"R4 Patient & Platform",IF(M95<=20,"R5 Harden","R6 Launch"))))) | O95: =L95*README!$B$32 | P95: NB-093 | Q95: Illegal transitions rejected; every transition audited | R95: Done
A96: NB-095 | B96: E10 Queue, Scheduling & Availability | C96: Queue | D96: Today / Arrivals screen | E96: Reception landing with arrivals, badges and quick check-in. | G96: Reception | H96: Clinic | I96: Frontend | J96: Must | K96: MVP | L96: 5 | M96: 9 | N96: =IF(M96<=4,"R1 Foundation",IF(M96<=8,"R2 Core Clinic",IF(M96<=13,"R3 Revenue & Messaging",IF(M96<=18,"R4 Patient & Platform",IF(M96<=20,"R5 Harden","R6 Launch"))))) | O96: =L96*README!$B$32 | P96: NB-094, NB-017 | Q96: Matches the wireframe; live-updates without refresh | R96: Done
A97: NB-096 | B97: E10 Queue, Scheduling & Availability | C97: Queue | D97: Real-time queue sync | E97: All roles see the same queue state within two seconds, degrading to polling. | F97: NFR-12 | G97: All | H97: Clinic | I97: Backend | J97: Must | K97: MVP | L97: 5 | M97: 9 | N97: =IF(M97<=4,"R1 Foundation",IF(M97<=8,"R2 Core Clinic",IF(M97<=13,"R3 Revenue & Messaging",IF(M97<=18,"R4 Patient & Platform",IF(M97<=20,"R5 Harden","R6 Launch"))))) | O97: =L97*README!$B$32 | P97: NB-094 | Q97: 2s propagation at 100 concurrent clients; fallback verified | R97: Not started
A98: NB-097 | B98: E10 Queue, Scheduling & Availability | C98: Queue | D98: Cancellation, reschedule & no-show handling | E98: Reason codes drawn from the shared reason list. | F98: SYS-07 | G98: Reception | H98: Clinic | I98: Fullstack | J98: Must | K98: MVP | L98: 5 | M98: 10 | N98: =IF(M98<=4,"R1 Foundation",IF(M98<=8,"R2 Core Clinic",IF(M98<=13,"R3 Revenue & Messaging",IF(M98<=18,"R4 Patient & Platform",IF(M98<=20,"R5 Harden","R6 Launch"))))) | O98: =L98*README!$B$32 | P98: NB-090, NB-011 | Q98: Reason mandatory; slot released immediately | R98: Done
A99: NB-098 | B99: E10 Queue, Scheduling & Availability | C99: Queue | D99: Smart overbooking protection | E99: Session caps count walk-ins and booked patients together; a full session is refused rather than silently overbooked. | F99: PAT-19 | G99: Reception,Patient | H99: Clinic | I99: Backend | J99: Must | K99: MVP | L99: 5 | M99: 11 | N99: =IF(M99<=4,"R1 Foundation",IF(M99<=8,"R2 Core Clinic",IF(M99<=13,"R3 Revenue & Messaging",IF(M99<=18,"R4 Patient & Platform",IF(M99<=20,"R5 Harden","R6 Launch"))))) | O99: =L99*README!$B$32 | P99: NB-090, NB-094 | Q99: Cap counts both intake paths; overbooking attempt is refused with a clear reason | R99: Done
A100: NB-099 | B100: E10 Queue, Scheduling & Availability | C100: Queue | D100: Waitlist & auto-fill offers | E100: A freed slot is offered to the waitlist with a 15-minute expiry. | F100: PAT-07,SYS-06 | G100: Reception,Patient | H100: Clinic | I100: Fullstack | J100: Should | K100: MVP | L100: 8 | M100: 12 | N100: =IF(M100<=4,"R1 Foundation",IF(M100<=8,"R2 Core Clinic",IF(M100<=13,"R3 Revenue & Messaging",IF(M100<=18,"R4 Patient & Platform",IF(M100<=20,"R5 Harden","R6 Launch"))))) | O100: =L100*README!$B$32 | P100: NB-090, NB-097 | Q100: Offer expires in 15 minutes and is re-offered in order; no double allocation | R100: Done
A101: NB-100 | B101: E10 Queue, Scheduling & Availability | C101: Queue | D101: Doctor delay broadcast ladder & clear-delay | E101: Two-step confirm writing the delay then closing and appending to history, with a Clear delay action. Treated as operationally urgent — not held for a prayer window. | F101: RCP-04,SYS-03 | G101: Reception | H101: Clinic | I101: Fullstack | J101: Must | K101: MVP | L101: 8 | M101: 13 | N101: =IF(M101<=4,"R1 Foundation",IF(M101<=8,"R2 Core Clinic",IF(M101<=13,"R3 Revenue & Messaging",IF(M101<=18,"R4 Patient & Platform",IF(M101<=20,"R5 Harden","R6 Launch"))))) | O101: =L101*README!$B$32 | P101: NB-094, NB-195 | Q101: Clear delay stops the announcement; delay broadcast bypasses the prayer-window hold | R101: Done
A102: NB-101 | B102: E10 Queue, Scheduling & Availability | C102: Queue | D102: Wait-time estimation | E102: Estimated wait derived from historical consultation durations per doctor. | F102: PAT-05 | G102: Reception,Patient | H102: Clinic | I102: Backend | J102: Could | K102: Phase 2 | L102: 5 | M102: 19 | N102: =IF(M102<=4,"R1 Foundation",IF(M102<=8,"R2 Core Clinic",IF(M102<=13,"R3 Revenue & Messaging",IF(M102<=18,"R4 Patient & Platform",IF(M102<=20,"R5 Harden","R6 Launch"))))) | O102: =L102*README!$B$32 | P102: NB-094 | Q102: Estimate within +/-25% on retrospective data | R102: Done
A103: NB-102 | B103: E11 Clinical Workspace | C103: Clinical | D103: Consultation workspace shell & session strip | E103: The doctor's primary screen. The session strip shows status before any detail. | F103: DOC-01 | G103: Doctor | H103: Clinic | I103: Frontend | J103: Must | K103: MVP | L103: 8 | M103: 11 | N103: =IF(M103<=4,"R1 Foundation",IF(M103<=8,"R2 Core Clinic",IF(M103<=13,"R3 Revenue & Messaging",IF(M103<=18,"R4 Patient & Platform",IF(M103<=20,"R5 Harden","R6 Launch"))))) | O103: =L103*README!$B$32 | P103: NB-094, NB-074 | Q103: A full consultation completes without leaving the screen | R103: Done
A104: NB-103 | B104: E11 Clinical Workspace | C104: Clinical | D104: Clinical note capture & templates | E104: Structured plus free-text notes, per-specialty templates, autosave. | F104: DOC-05 | G104: Doctor | H104: Clinic | I104: Fullstack | J104: Must | K104: MVP | L104: 8 | M104: 11 | N104: =IF(M104<=4,"R1 Foundation",IF(M104<=8,"R2 Core Clinic",IF(M104<=13,"R3 Revenue & Messaging",IF(M104<=18,"R4 Patient & Platform",IF(M104<=20,"R5 Harden","R6 Launch"))))) | O104: =L104*README!$B$32 | P104: NB-102 | Q104: No note loss on crash or lock; autosave every 10s | R104: Done
A105: NB-104 | B105: E11 Clinical Workspace | C105: Clinical | D105: Clinical note amendment & versioning | E105: Signed notes are immutable; amendments append with reason and author. | F105: SYS-13 | G105: Doctor | H105: Clinic | I105: Backend | J105: Must | K105: MVP | L105: 5 | M105: 12 | N105: =IF(M105<=4,"R1 Foundation",IF(M105<=8,"R2 Core Clinic",IF(M105<=13,"R3 Revenue & Messaging",IF(M105<=18,"R4 Patient & Platform",IF(M105<=20,"R5 Harden","R6 Launch"))))) | O105: =L105*README!$B$32 | P105: NB-103, NB-238 | Q105: Original text always retrievable; amendment reason mandatory | R105: Done
A106: NB-105 | B106: E11 Clinical Workspace | C106: Clinical | D106: Previous medicines & treatment view | E106: Read before prescribing — prior therapy surfaced in the prescribing path. | F106: DOC-02,GP-06 | G106: Doctor | H106: Clinic | I106: Frontend | J106: Must | K106: MVP | L106: 5 | M106: 12 | N106: =IF(M106<=4,"R1 Foundation",IF(M106<=8,"R2 Core Clinic",IF(M106<=13,"R3 Revenue & Messaging",IF(M106<=18,"R4 Patient & Platform",IF(M106<=20,"R5 Harden","R6 Launch"))))) | O106: =L106*README!$B$32 | P106: NB-102, NB-109 | Q106: Prior medication is visible without leaving the prescription pad | R106: Done
...

Sheet Requirement Coverage
A1: Requirement coverage — every identifier found in the wireframe, and the tasks that deliver it
A2: Extracted programmatically from the wireframe source, not transcribed by hand. Uncovered rows turn red — there must be none.
A4: Requirement ID | B4: Area | C4: Description (from the wireframe) | D4: Work Starts In | E4: Tasks Delivering It | F4: Task Count | G4: Covered?
A5: AGG-01 | B5: Aggregator | C5: Nabd's shared number, invisible routing, verified-visit ratings | D5: MVP | E5: NB-221, NB-224, NB-288 | F5: 3 | G5: =IF(F5>0,"Yes","NO")
A6: AGG-02 | B6: Aggregator | C6: This may be an emergency. Call | D6: Phase 2 | E6: NB-222 | F6: 1 | G6: =IF(F6>0,"Yes","NO")
A7: AGG-03 | B7: Aggregator | D7: Phase 2 | E7: NB-223 | F7: 1 | G7: =IF(F7>0,"Yes","NO")
A8: AGG-04 | B8: Aggregator | C8: patient demand on the unified number vs actual coverage — the sales signal | D8: Phase 2 | E8: NB-227, NB-270 | F8: 2 | G8: =IF(F8>0,"Yes","NO")
A9: AGG-05 | B9: Aggregator | C9: A verified rating comes only from a completed, paid visit on the platform — fake reviews are impossible. Hidden until 10 ratings, showing \ | D9: Phase 2 | E9: NB-225, NB-226 | F9: 2 | G9: =IF(F9>0,"Yes","NO")
A10: AYU-02 | B10: Ayurveda | C10: Panchakarma | D10: Phase 2 | E10: NB-140 | F10: 1 | G10: =IF(F10>0,"Yes","NO")
A11: AYU-03 | B11: Ayurveda | C11: Herbal formulation (Ayurveda) | D11: Phase 2 | E11: NB-140 | F11: 1 | G11: =IF(F11>0,"Yes","NO")
A12: BIL-06 | B12: Billing | C12: Dues list | D12: MVP | E12: NB-171, NB-233 | F12: 2 | G12: =IF(F12>0,"Yes","NO")
A13: BIL-07 | B13: Billing | C13: Price transparency & estimates | D13: MVP | E13: NB-126, NB-170 | F13: 2 | G13: =IF(F13>0,"Yes","NO")
A14: BIL-11 | B14: Billing | C14: Insurance claim export | D14: MVP | E14: NB-070, NB-175 | F14: 2 | G14: =IF(F14>0,"Yes","NO")
A15: CAD-01 | B15: Setup | C15: Guided clinic setup wizard | D15: MVP | E15: NB-060, NB-069, NB-339 | F15: 3 | G15: =IF(F15>0,"Yes","NO")
A16: CAD-04 | B16: Setup | C16: CAD-04 · 24 charge heads | D16: MVP | E16: NB-061 | F16: 1 | G16: =IF(F16>0,"Yes","NO")
A17: CAD-05 | B17: Setup | C17: Schedule and calendar admin | D17: MVP | E17: NB-036, NB-064, NB-090, NB-091, NB-092 | F17: 5 | G17: =IF(F17>0,"Yes","NO")
A18: CAD-06 | B18: Setup | C18: Simple policy settings | D18: MVP | E18: NB-062 | F18: 1 | G18: =IF(F18>0,"Yes","NO")
A19: CAD-07 | B19: Setup | C19: WhatsApp number & template health | D19: MVP | E19: NB-069, NB-188, NB-189, NB-190, NB-239 | F19: 5 | G19: =IF(F19>0,"Yes","NO")
... A85: MKT-04 | B85: Marketing | C85: Influencer & social attribution | D85: MVP | E85: NB-079, NB-230 | F85: 2 | G85: =IF(F85>0,"Yes","NO")
A86: NFR-02 | B86: Non-func. | D86: MVP | E86: NB-006, NB-024, NB-029, NB-200, NB-273, NB-288, NB-316, NB-324, NB-327, NB-331 | F86: 10 | G86: =IF(F86>0,"Yes","NO")
A87: NFR-04 | B87: Non-func. | C87: no cross-region replication, region-scoped KMS keys | D87: MVP | E87: NB-001, NB-002, NB-254, NB-271, NB-283, NB-299, NB-306 | F87: 7 | G87: =IF(F87>0,"Yes","NO")
A88: NFR-06 | B88: Non-func. | D88: MVP | E88: NB-040, NB-042 | F88: 2 | G88: =IF(F88>0,"Yes","NO")
A89: NFR-07 | B89: Non-func. | C89: Regulator/owner export within 72h — NFR-07 · 3-year retention. | D89: MVP | E89: NB-078, NB-244, NB-247, NB-253 | F89: 4 | G89: =IF(F89>0,"Yes","NO")
A90: NFR-08 | B90: Non-func. | C90: Consent is checked at query level — NFR-08. | D90: MVP | E90: NB-053, NB-196, NB-241 | F90: 3 | G90: =IF(F90>0,"Yes","NO")
A91: NFR-09 | B91: Non-func. | C91: Annual CERT-In-empanelled VAPT (NFR-09) · annual drill with tenants. | D91: MVP | E91: NB-294, NB-295, NB-348 | F91: 3 | G91: =IF(F91>0,"Yes","NO")
A92: NFR-12 | B92: Non-func. | C92: A sync queue means a clinic working offline, not lost data. WhatsApp quality under 60% puts sending at risk. | D92: MVP | E92: NB-007, NB-020, NB-096, NB-263, NB-327, NB-328, NB-330, NB-341 | F92: 8 | G92: =IF(F92>0,"Yes","NO")
A93: NFR-18 | B93: Non-func. | C93: Fully self-serve, no support help needed — NFR-18. | D93: MVP | E93: NB-060, NB-068, NB-345 | F93: 3 | G93: =IF(F93>0,"Yes","NO")
A94: NUR-05 | B94: Nursing | C94: Clinical triage inbox | D94: MVP | E94: NB-144 | F94: 1 | G94: =IF(F94>0,"Yes","NO")
A95: ORTH-01 | B95: Ortho | C95: X-ray attach & review flag | D95: MVP | E95: NB-135 | F95: 1 | G95: =IF(F95>0,"Yes","NO")
A96: ORTH-02 | B96: Ortho | C96: Fracture/injury note templates | D96: MVP | E96: NB-135 | F96: 1 | G96: =IF(F96>0,"Yes","NO")
A97: ORTH-03 | B97: Ortho | C97: Physio session packages | D97: Phase 2 | E97: NB-136 | F97: 1 | G97: =IF(F97>0,"Yes","NO")
A98: OWN-01 | B98: Owner | C98: Daily money dashboard | D98: MVP | E98: NB-025, NB-229, NB-324, NB-332 | F98: 4 | G98: =IF(F98>0,"Yes","NO")
A99: OWN-02 | B99: Owner | C99: Where patients come from | D99: MVP | E99: NB-079, NB-230 | F99: 2 | G99: =IF(F99>0,"Yes","NO")
A100: OWN-03 | B100: Owner | C100: Repeat-patient & recall value | D100: Phase 2 | E100: NB-234 | F100: 1 | G100: =IF(F100>0,"Yes","NO")
... A189: SYS-25 | B189: Platform | C189: The clinic never touches Meta Business Manager — SYS-25 is a fully managed service. | D189: MVP | E189: NB-188 | F189: 1 | G189: =IF(F189>0,"Yes","NO")
A191: TOTAL | C191: ="Requirements in register: "&COUNTA(A5:A189) | F191: =SUM(F5:F189) | G191: =COUNTIF(G5:G189,"NO")&" uncovered"

Sheet Epics
A1: Epic rollup — every cell is a formula reading the Backlog tab
A3: Epic | B3: Tasks | C3: Story Points | D3: % of Total | E3: Est. Person-Days | F3: Must | G3: Should | H3: Could | I3: MVP | J3: Phase 2 | K3: Phase 3 | L3: First Sprint | M3: Last Sprint | N3: Done | O3: % Complete
A4: E01 Foundation & Architecture | B4: =COUNTIF(Backlog!$B$2:$B$352,$A4) | C4: =SUMIF(Backlog!$B$2:$B$352,$A4,Backlog!$L$2:$L$352) | D4: =IFERROR(C4/$C$33,0) | E4: =C4*README!$B$32 | F4: =COUNTIFS(Backlog!$B$2:$B$352,$A4,Backlog!$J$2:$J$352,"Must") | G4: =COUNTIFS(Backlog!$B$2:$B$352,$A4,Backlog!$J$2:$J$352,"Should") | H4: =COUNTIFS(Backlog!$B$2:$B$352,$A4,Backlog!$J$2:$J$352,"Could") | I4: =COUNTIFS(Backlog!$B$2:$B$352,$A4,Backlog!$K$2:$K$352,"MVP") | J4: =COUNTIFS(Backlog!$B$2:$B$352,$A4,Backlog!$K$2:$K$352,"Phase 2") | K4: =COUNTIFS(Backlog!$B$2:$B$352,$A4,Backlog!$K$2:$K$352,"Phase 3") | L4: =_xlfn.MINIFS(Backlog!$M$2:$M$352,Backlog!$B$2:$B$352,$A4) | M4: =_xlfn.MAXIFS(Backlog!$M$2:$M$352,Backlog!$B$2:$B$352,$A4) | N4: =COUNTIFS(Backlog!$B$2:$B$352,$A4,Backlog!$R$2:$R$352,"Done") | O4: =IFERROR(N4/B4,0)
A5: E02 Design System & UI Kit | B5: =COUNTIF(Backlog!$B$2:$B$352,$A5) | C5: =SUMIF(Backlog!$B$2:$B$352,$A5,Backlog!$L$2:$L$352) | D5: =IFERROR(C5/$C$33,0) | E5: =C5*README!$B$32 | F5: =COUNTIFS(Backlog!$B$2:$B$352,$A5,Backlog!$J$2:$J$352,"Must") | G5: =COUNTIFS(Backlog!$B$2:$B$352,$A5,Backlog!$J$2:$J$352,"Should") | H5: =COUNTIFS(Backlog!$B$2:$B$352,$A5,Backlog!$J$2:$J$352,"Could") | I5: =COUNTIFS(Backlog!$B$2:$B$352,$A5,Backlog!$K$2:$K$352,"MVP") | J5: =COUNTIFS(Backlog!$B$2:$B$352,$A5,Backlog!$K$2:$K$352,"Phase 2") | K5: =COUNTIFS(Backlog!$B$2:$B$352,$A5,Backlog!$K$2:$K$352,"Phase 3") | L5: =_xlfn.MINIFS(Backlog!$M$2:$M$352,Backlog!$B$2:$B$352,$A5) | M5: =_xlfn.MAXIFS(Backlog!$M$2:$M$352,Backlog!$B$2:$B$352,$A5) | N5: =COUNTIFS(Backlog!$B$2:$B$352,$A5,Backlog!$R$2:$R$352,"Done") | O5: =IFERROR(N5/B5,0)
A6: E03 Chart & Data-Visualisation System | B6: =COUNTIF(Backlog!$B$2:$B$352,$A6) | C6: =SUMIF(Backlog!$B$2:$B$352,$A6,Backlog!$L$2:$L$352) | D6: =IFERROR(C6/$C$33,0) | E6: =C6*README!$B$32 | F6: =COUNTIFS(Backlog!$B$2:$B$352,$A6,Backlog!$J$2:$J$352,"Must") | G6: =COUNTIFS(Backlog!$B$2:$B$352,$A6,Backlog!$J$2:$J$352,"Should") | H6: =COUNTIFS(Backlog!$B$2:$B$352,$A6,Backlog!$J$2:$J$352,"Could") | I6: =COUNTIFS(Backlog!$B$2:$B$352,$A6,Backlog!$K$2:$K$352,"MVP") | J6: =COUNTIFS(Backlog!$B$2:$B$352,$A6,Backlog!$K$2:$K$352,"Phase 2") | K6: =COUNTIFS(Backlog!$B$2:$B$352,$A6,Backlog!$K$2:$K$352,"Phase 3") | L6: =_xlfn.MINIFS(Backlog!$M$2:$M$352,Backlog!$B$2:$B$352,$A6) | M6: =_xlfn.MAXIFS(Backlog!$M$2:$M$352,Backlog!$B$2:$B$352,$A6) | N6: =COUNTIFS(Backlog!$B$2:$B$352,$A6,Backlog!$R$2:$R$352,"Done") | O6: =IFERROR(N6/B6,0)
A7: E04 Localisation, RTL & i18n | B7: =COUNTIF(Backlog!$B$2:$B$352,$A7) | C7: =SUMIF(Backlog!$B$2:$B$352,$A7,Backlog!$L$2:$L$352) | D7: =IFERROR(C7/$C$33,0) | E7: =C7*README!$B$32 | F7: =COUNTIFS(Backlog!$B$2:$B$352,$A7,Backlog!$J$2:$J$352,"Must") | G7: =COUNTIFS(Backlog!$B$2:$B$352,$A7,Backlog!$J$2:$J$352,"Should") | H7: =COUNTIFS(Backlog!$B$2:$B$352,$A7,Backlog!$J$2:$J$352,"Could") | I7: =COUNTIFS(Backlog!$B$2:$B$352,$A7,Backlog!$K$2:$K$352,"MVP") | J7: =COUNTIFS(Backlog!$B$2:$B$352,$A7,Backlog!$K$2:$K$352,"Phase 2") | K7: =COUNTIFS(Backlog!$B$2:$B$352,$A7,Backlog!$K$2:$K$352,"Phase 3") | L7: =_xlfn.MINIFS(Backlog!$M$2:$M$352,Backlog!$B$2:$B$352,$A7) | M7: =_xlfn.MAXIFS(Backlog!$M$2:$M$352,Backlog!$B$2:$B$352,$A7) | N7: =COUNTIFS(Backlog!$B$2:$B$352,$A7,Backlog!$R$2:$R$352,"Done") | O7: =IFERROR(N7/B7,0)
A8: E05 Identity, Auth & Session | B8: =COUNTIF(Backlog!$B$2:$B$352,$A8) | C8: =SUMIF(Backlog!$B$2:$B$352,$A8,Backlog!$L$2:$L$352) | D8: =IFERROR(C8/$C$33,0) | E8: =C8*README!$B$32 | F8: =COUNTIFS(Backlog!$B$2:$B$352,$A8,Backlog!$J$2:$J$352,"Must") | G8: =COUNTIFS(Backlog!$B$2:$B$352,$A8,Backlog!$J$2:$J$352,"Should") | H8: =COUNTIFS(Backlog!$B$2:$B$352,$A8,Backlog!$J$2:$J$352,"Could") | I8: =COUNTIFS(Backlog!$B$2:$B$352,$A8,Backlog!$K$2:$K$352,"MVP") | J8: =COUNTIFS(Backlog!$B$2:$B$352,$A8,Backlog!$K$2:$K$352,"Phase 2") | K8: =COUNTIFS(Backlog!$B$2:$B$352,$A8,Backlog!$K$2:$K$352,"Phase 3") | L8: =_xlfn.MINIFS(Backlog!$M$2:$M$352,Backlog!$B$2:$B$352,$A8) | M8: =_xlfn.MAXIFS(Backlog!$M$2:$M$352,Backlog!$B$2:$B$352,$A8) | N8: =COUNTIFS(Backlog!$B$2:$B$352,$A8,Backlog!$R$2:$R$352,"Done") | O8: =IFERROR(N8/B8,0)
A9: E06 RBAC & Permissions | B9: =COUNTIF(Backlog!$B$2:$B$352,$A9) | C9: =SUMIF(Backlog!$B$2:$B$352,$A9,Backlog!$L$2:$L$352) | D9: =IFERROR(C9/$C$33,0) | E9: =C9*README!$B$32 | F9: =COUNTIFS(Backlog!$B$2:$B$352,$A9,Backlog!$J$2:$J$352,"Must") | G9: =COUNTIFS(Backlog!$B$2:$B$352,$A9,Backlog!$J$2:$J$352,"Should") | H9: =COUNTIFS(Backlog!$B$2:$B$352,$A9,Backlog!$J$2:$J$352,"Could") | I9: =COUNTIFS(Backlog!$B$2:$B$352,$A9,Backlog!$K$2:$K$352,"MVP") | J9: =COUNTIFS(Backlog!$B$2:$B$352,$A9,Backlog!$K$2:$K$352,"Phase 2") | K9: =COUNTIFS(Backlog!$B$2:$B$352,$A9,Backlog!$K$2:$K$352,"Phase 3") | L9: =_xlfn.MINIFS(Backlog!$M$2:$M$352,Backlog!$B$2:$B$352,$A9) | M9: =_xlfn.MAXIFS(Backlog!$M$2:$M$352,Backlog!$B$2:$B$352,$A9) | N9: =COUNTIFS(Backlog!$B$2:$B$352,$A9,Backlog!$R$2:$R$352,"Done") | O9: =IFERROR(N9/B9,0)
A10: E07 Clinic Setup & Administration | B10: =COUNTIF(Backlog!$B$2:$B$352,$A10) | C10: =SUMIF(Backlog!$B$2:$B$352,$A10,Backlog!$L$2:$L$352) | D10: =IFERROR(C10/$C$33,0) | E10: =C10*README!$B$32 | F10: =COUNTIFS(Backlog!$B$2:$B$352,$A10,Backlog!$J$2:$J$352,"Must") | G10: =COUNTIFS(Backlog!$B$2:$B$352,$A10,Backlog!$J$2:$J$352,"Should") | H10: =COUNTIFS(Backlog!$B$2:$B$352,$A10,Backlog!$J$2:$J$352,"Could") | I10: =COUNTIFS(Backlog!$B$2:$B$352,$A10,Backlog!$K$2:$K$352,"MVP") | J10: =COUNTIFS(Backlog!$B$2:$B$352,$A10,Backlog!$K$2:$K$352,"Phase 2") | K10: =COUNTIFS(Backlog!$B$2:$B$352,$A10,Backlog!$K$2:$K$352,"Phase 3") | L10: =_xlfn.MINIFS(Backlog!$M$2:$M$352,Backlog!$B$2:$B$352,$A10) | M10: =_xlfn.MAXIFS(Backlog!$M$2:$M$352,Backlog!$B$2:$B$352,$A10) | N10: =COUNTIFS(Backlog!$B$2:$B$352,$A10,Backlog!$R$2:$R$352,"Done") | O10: =IFERROR(N10/B10,0)
A11: E08 Patient Records & Registration | B11: =COUNTIF(Backlog!$B$2:$B$352,$A11) | C11: =SUMIF(Backlog!$B$2:$B$352,$A11,Backlog!$L$2:$L$352) | D11: =IFERROR(C11/$C$33,0) | E11: =C11*README!$B$32 | F11: =COUNTIFS(Backlog!$B$2:$B$352,$A11,Backlog!$J$2:$J$352,"Must") | G11: =COUNTIFS(Backlog!$B$2:$B$352,$A11,Backlog!$J$2:$J$352,"Should") | H11: =COUNTIFS(Backlog!$B$2:$B$352,$A11,Backlog!$J$2:$J$352,"Could") | I11: =COUNTIFS(Backlog!$B$2:$B$352,$A11,Backlog!$K$2:$K$352,"MVP") | J11: =COUNTIFS(Backlog!$B$2:$B$352,$A11,Backlog!$K$2:$K$352,"Phase 2") | K11: =COUNTIFS(Backlog!$B$2:$B$352,$A11,Backlog!$K$2:$K$352,"Phase 3") | L11: =_xlfn.MINIFS(Backlog!$M$2:$M$352,Backlog!$B$2:$B$352,$A11) | M11: =_xlfn.MAXIFS(Backlog!$M$2:$M$352,Backlog!$B$2:$B$352,$A11) | N11: =COUNTIFS(Backlog!$B$2:$B$352,$A11,Backlog!$R$2:$R$352,"Done") | O11: =IFERROR(N11/B11,0)
A12: E09 Caregiver, Family & Guardianship | B12: =COUNTIF(Backlog!$B$2:$B$352,$A12) | C12: =SUMIF(Backlog!$B$2:$B$352,$A12,Backlog!$L$2:$L$352) | D12: =IFERROR(C12/$C$33,0) | E12: =C12*README!$B$32 | F12: =COUNTIFS(Backlog!$B$2:$B$352,$A12,Backlog!$J$2:$J$352,"Must") | G12: =COUNTIFS(Backlog!$B$2:$B$352,$A12,Backlog!$J$2:$J$352,"Should") | H12: =COUNTIFS(Backlog!$B$2:$B$352,$A12,Backlog!$J$2:$J$352,"Could") | I12: =COUNTIFS(Backlog!$B$2:$B$352,$A12,Backlog!$K$2:$K$352,"MVP") | J12: =COUNTIFS(Backlog!$B$2:$B$352,$A12,Backlog!$K$2:$K$352,"Phase 2") | K12: =COUNTIFS(Backlog!$B$2:$B$352,$A12,Backlog!$K$2:$K$352,"Phase 3") | L12: =_xlfn.MINIFS(Backlog!$M$2:$M$352,Backlog!$B$2:$B$352,$A12) | M12: =_xlfn.MAXIFS(Backlog!$M$2:$M$352,Backlog!$B$2:$B$352,$A12) | N12: =COUNTIFS(Backlog!$B$2:$B$352,$A12,Backlog!$R$2:$R$352,"Done") | O12: =IFERROR(N12/B12,0)
A13: E10 Queue, Scheduling & Availability | B13: =COUNTIF(Backlog!$B$2:$B$352,$A13) | C13: =SUMIF(Backlog!$B$2:$B$352,$A13,Backlog!$L$2:$L$352) | D13: =IFERROR(C13/$C$33,0) | E13: =C13*README!$B$32 | F13: =COUNTIFS(Backlog!$B$2:$B$352,$A13,Backlog!$J$2:$J$352,"Must") | G13: =COUNTIFS(Backlog!$B$2:$B$352,$A13,Backlog!$J$2:$J$352,"Should") | H13: =COUNTIFS(Backlog!$B$2:$B$352,$A13,Backlog!$J$2:$J$352,"Could") | I13: =COUNTIFS(Backlog!$B$2:$B$352,$A13,Backlog!$K$2:$K$352,"MVP") | J13: =COUNTIFS(Backlog!$B$2:$B$352,$A13,Backlog!$K$2:$K$352,"Phase 2") | K13: =COUNTIFS(Backlog!$B$2:$B$352,$A13,Backlog!$K$2:$K$352,"Phase 3") | L13: =_xlfn.MINIFS(Backlog!$M$2:$M$352,Backlog!$B$2:$B$352,$A13) | M13: =_xlfn.MAXIFS(Backlog!$M$2:$M$352,Backlog!$B$2:$B$352,$A13) | N13: =COUNTIFS(Backlog!$B$2:$B$352,$A13,Backlog!$R$2:$R$352,"Done") | O13: =IFERROR(N13/B13,0)
A14: E11 Clinical Workspace | B14: =COUNTIF(Backlog!$B$2:$B$352,$A14) | C14: =SUMIF(Backlog!$B$2:$B$352,$A14,Backlog!$L$2:$L$352) | D14: =IFERROR(C14/$C$33,0) | E14: =C14*README!$B$32 | F14: =COUNTIFS(Backlog!$B$2:$B$352,$A14,Backlog!$J$2:$J$352,"Must") | G14: =COUNTIFS(Backlog!$B$2:$B$352,$A14,Backlog!$J$2:$J$352,"Should") | H14: =COUNTIFS(Backlog!$B$2:$B$352,$A14,Backlog!$J$2:$J$352,"Could") | I14: =COUNTIFS(Backlog!$B$2:$B$352,$A14,Backlog!$K$2:$K$352,"MVP") | J14: =COUNTIFS(Backlog!$B$2:$B$352,$A14,Backlog!$K$2:$K$352,"Phase 2") | K14: =COUNTIFS(Backlog!$B$2:$B$352,$A14,Backlog!$K$2:$K$352,"Phase 3") | L14: =_xlfn.MINIFS(Backlog!$M$2:$M$352,Backlog!$B$2:$B$352,$A14) | M14: =_xlfn.MAXIFS(Backlog!$M$2:$M$352,Backlog!$B$2:$B$352,$A14) | N14: =COUNTIFS(Backlog!$B$2:$B$352,$A14,Backlog!$R$2:$R$352,"Done") | O14: =IFERROR(N14/B14,0)
A15: E12 Specialty Workspaces | B15: =COUNTIF(Backlog!$B$2:$B$352,$A15) | C15: =SUMIF(Backlog!$B$2:$B$352,$A15,Backlog!$L$2:$L$352) | D15: =IFERROR(C15/$C$33,0) | E15: =C15*README!$B$32 | F15: =COUNTIFS(Backlog!$B$2:$B$352,$A15,Backlog!$J$2:$J$352,"Must") | G15: =COUNTIFS(Backlog!$B$2:$B$352,$A15,Backlog!$J$2:$J$352,"Should") | H15: =COUNTIFS(Backlog!$B$2:$B$352,$A15,Backlog!$J$2:$J$352,"Could") | I15: =COUNTIFS(Backlog!$B$2:$B$352,$A15,Backlog!$K$2:$K$352,"MVP") | J15: =COUNTIFS(Backlog!$B$2:$B$352,$A15,Backlog!$K$2:$K$352,"Phase 2") | K15: =COUNTIFS(Backlog!$B$2:$B$352,$A15,Backlog!$K$2:$K$352,"Phase 3") | L15: =_xlfn.MINIFS(Backlog!$M$2:$M$352,Backlog!$B$2:$B$352,$A15) | M15: =_xlfn.MAXIFS(Backlog!$M$2:$M$352,Backlog!$B$2:$B$352,$A15) | N15: =COUNTIFS(Backlog!$B$2:$B$352,$A15,Backlog!$R$2:$R$352,"Done") | O15: =IFERROR(N15/B15,0)
... A32: E29 Launch, Migration & Handover | B32: =COUNTIF(Backlog!$B$2:$B$352,$A32) | C32: =SUMIF(Backlog!$B$2:$B$352,$A32,Backlog!$L$2:$L$352) | D32: =IFERROR(C32/$C$33,0) | E32: =C32*README!$B$32 | F32: =COUNTIFS(Backlog!$B$2:$B$352,$A32,Backlog!$J$2:$J$352,"Must") | G32: =COUNTIFS(Backlog!$B$2:$B$352,$A32,Backlog!$J$2:$J$352,"Should") | H32: =COUNTIFS(Backlog!$B$2:$B$352,$A32,Backlog!$J$2:$J$352,"Could") | I32: =COUNTIFS(Backlog!$B$2:$B$352,$A32,Backlog!$K$2:$K$352,"MVP") | J32: =COUNTIFS(Backlog!$B$2:$B$352,$A32,Backlog!$K$2:$K$352,"Phase 2") | K32: =COUNTIFS(Backlog!$B$2:$B$352,$A32,Backlog!$K$2:$K$352,"Phase 3") | L32: =_xlfn.MINIFS(Backlog!$M$2:$M$352,Backlog!$B$2:$B$352,$A32) | M32: =_xlfn.MAXIFS(Backlog!$M$2:$M$352,Backlog!$B$2:$B$352,$A32) | N32: =COUNTIFS(Backlog!$B$2:$B$352,$A32,Backlog!$R$2:$R$352,"Done") | O32: =IFERROR(N32/B32,0)
A33: TOTAL | B33: =SUM(B4:B32) | C33: =SUM(C4:C32) | D33: =SUM(D4:D32) | E33: =SUM(E4:E32) | F33: =SUM(F4:F32) | G33: =SUM(G4:G32) | H33: =SUM(H4:H32) | I33: =SUM(I4:I32) | ... K33: =SUM(K4:K32) | L33: =MIN(L4:L32) | M33: =MAX(M4:M32) | N33: =SUM(N4:N32) | O33: =IFERROR(N33/B33,0)

Sheet Sprints
A1: Sprint load against ramped squad capacity
A2: Capacity = squads that sprint x README!B31. Squad counts are blue input cells — change them and every capacity figure moves.
A4: Sprint | B4: Release Band | C4: Squads | D4: Capacity | E4: Tasks | F4: Story Points | G4: Head-room | H4: Utilisation | I4: Est. Person-Days | J4: Must Tasks | K4: Cumulative Points | L4: % of Programme
A5: 1 | B5: =IF(A5<=4,"R1 Foundation",IF(A5<=8,"R2 Core Clinic",IF(A5<=13,"R3 Revenue & Messaging",IF(A5<=18,"R4 Patient & Platform",IF(A5<=20,"R5 Harden","R6 Launch"))))) | C5: 2 | D5: =C5*README!$B$31 | E5: =COUNTIF(Backlog!$M$2:$M$352,$A5) | F5: =SUMIF(Backlog!$M$2:$M$352,$A5,Backlog!$L$2:$L$352) | G5: =D5-F5 | H5: =IFERROR(F5/D5,0) | I5: =F5*README!$B$32 | J5: =COUNTIFS(Backlog!$M$2:$M$352,$A5,Backlog!$J$2:$J$352,"Must") | K5: =SUM($F$5:F5) | L5: =IFERROR(K5/SUM($F$5:$F$27),0)
A6: 2 | B6: =IF(A6<=4,"R1 Foundation",IF(A6<=8,"R2 Core Clinic",IF(A6<=13,"R3 Revenue & Messaging",IF(A6<=18,"R4 Patient & Platform",IF(A6<=20,"R5 Harden","R6 Launch"))))) | C6: 2 | D6: =C6*README!$B$31 | E6: =COUNTIF(Backlog!$M$2:$M$352,$A6) | F6: =SUMIF(Backlog!$M$2:$M$352,$A6,Backlog!$L$2:$L$352) | G6: =D6-F6 | H6: =IFERROR(F6/D6,0) | I6: =F6*README!$B$32 | J6: =COUNTIFS(Backlog!$M$2:$M$352,$A6,Backlog!$J$2:$J$352,"Must") | K6: =SUM($F$5:F6) | L6: =IFERROR(K6/SUM($F$5:$F$27),0)
A7: 3 | B7: =IF(A7<=4,"R1 Foundation",IF(A7<=8,"R2 Core Clinic",IF(A7<=13,"R3 Revenue & Messaging",IF(A7<=18,"R4 Patient & Platform",IF(A7<=20,"R5 Harden","R6 Launch"))))) | C7: 2 | D7: =C7*README!$B$31 | E7: =COUNTIF(Backlog!$M$2:$M$352,$A7) | F7: =SUMIF(Backlog!$M$2:$M$352,$A7,Backlog!$L$2:$L$352) | G7: =D7-F7 | H7: =IFERROR(F7/D7,0) | I7: =F7*README!$B$32 | J7: =COUNTIFS(Backlog!$M$2:$M$352,$A7,Backlog!$J$2:$J$352,"Must") | K7: =SUM($F$5:F7) | L7: =IFERROR(K7/SUM($F$5:$F$27),0)
A8: 4 | B8: =IF(A8<=4,"R1 Foundation",IF(A8<=8,"R2 Core Clinic",IF(A8<=13,"R3 Revenue & Messaging",IF(A8<=18,"R4 Patient & Platform",IF(A8<=20,"R5 Harden","R6 Launch"))))) | C8: 2 | D8: =C8*README!$B$31 | E8: =COUNTIF(Backlog!$M$2:$M$352,$A8) | F8: =SUMIF(Backlog!$M$2:$M$352,$A8,Backlog!$L$2:$L$352) | G8: =D8-F8 | H8: =IFERROR(F8/D8,0) | I8: =F8*README!$B$32 | J8: =COUNTIFS(Backlog!$M$2:$M$352,$A8,Backlog!$J$2:$J$352,"Must") | K8: =SUM($F$5:F8) | L8: =IFERROR(K8/SUM($F$5:$F$27),0)
A9: 5 | B9: =IF(A9<=4,"R1 Foundation",IF(A9<=8,"R2 Core Clinic",IF(A9<=13,"R3 Revenue & Messaging",IF(A9<=18,"R4 Patient & Platform",IF(A9<=20,"R5 Harden","R6 Launch"))))) | C9: 2 | D9: =C9*README!$B$31 | E9: =COUNTIF(Backlog!$M$2:$M$352,$A9) | F9: =SUMIF(Backlog!$M$2:$M$352,$A9,Backlog!$L$2:$L$352) | G9: =D9-F9 | H9: =IFERROR(F9/D9,0) | I9: =F9*README!$B$32 | J9: =COUNTIFS(Backlog!$M$2:$M$352,$A9,Backlog!$J$2:$J$352,"Must") | K9: =SUM($F$5:F9) | L9: =IFERROR(K9/SUM($F$5:$F$27),0)
A10: 6 | B10: =IF(A10<=4,"R1 Foundation",IF(A10<=8,"R2 Core Clinic",IF(A10<=13,"R3 Revenue & Messaging",IF(A10<=18,"R4 Patient & Platform",IF(A10<=20,"R5 Harden","R6 Launch"))))) | C10: 2 | D10: =C10*README!$B$31 | E10: =COUNTIF(Backlog!$M$2:$M$352,$A10) | F10: =SUMIF(Backlog!$M$2:$M$352,$A10,Backlog!$L$2:$L$352) | G10: =D10-F10 | H10: =IFERROR(F10/D10,0) | I10: =F10*README!$B$32 | J10: =COUNTIFS(Backlog!$M$2:$M$352,$A10,Backlog!$J$2:$J$352,"Must") | K10: =SUM($F$5:F10) | L10: =IFERROR(K10/SUM($F$5:$F$27),0)
A11: 7 | B11: =IF(A11<=4,"R1 Foundation",IF(A11<=8,"R2 Core Clinic",IF(A11<=13,"R3 Revenue & Messaging",IF(A11<=18,"R4 Patient & Platform",IF(A11<=20,"R5 Harden","R6 Launch"))))) | C11: 3 | D11: =C11*README!$B$31 | E11: =COUNTIF(Backlog!$M$2:$M$352,$A11) | F11: =SUMIF(Backlog!$M$2:$M$352,$A11,Backlog!$L$2:$L$352) | G11: =D11-F11 | H11: =IFERROR(F11/D11,0) | I11: =F11*README!$B$32 | J11: =COUNTIFS(Backlog!$M$2:$M$352,$A11,Backlog!$J$2:$J$352,"Must") | K11: =SUM($F$5:F11) | L11: =IFERROR(K11/SUM($F$5:$F$27),0)
A12: 8 | B12: =IF(A12<=4,"R1 Foundation",IF(A12<=8,"R2 Core Clinic",IF(A12<=13,"R3 Revenue & Messaging",IF(A12<=18,"R4 Patient & Platform",IF(A12<=20,"R5 Harden","R6 Launch"))))) | C12: 2 | D12: =C12*README!$B$31 | E12: =COUNTIF(Backlog!$M$2:$M$352,$A12) | F12: =SUMIF(Backlog!$M$2:$M$352,$A12,Backlog!$L$2:$L$352) | G12: =D12-F12 | H12: =IFERROR(F12/D12,0) | I12: =F12*README!$B$32 | J12: =COUNTIFS(Backlog!$M$2:$M$352,$A12,Backlog!$J$2:$J$352,"Must") | K12: =SUM($F$5:F12) | L12: =IFERROR(K12/SUM($F$5:$F$27),0)
A13: 9 | B13: =IF(A13<=4,"R1 Foundation",IF(A13<=8,"R2 Core Clinic",IF(A13<=13,"R3 Revenue & Messaging",IF(A13<=18,"R4 Patient & Platform",IF(A13<=20,"R5 Harden","R6 Launch"))))) | C13: 3 | D13: =C13*README!$B$31 | E13: =COUNTIF(Backlog!$M$2:$M$352,$A13) | F13: =SUMIF(Backlog!$M$2:$M$352,$A13,Backlog!$L$2:$L$352) | G13: =D13-F13 | H13: =IFERROR(F13/D13,0) | I13: =F13*README!$B$32 | J13: =COUNTIFS(Backlog!$M$2:$M$352,$A13,Backlog!$J$2:$J$352,"Must") | K13: =SUM($F$5:F13) | L13: =IFERROR(K13/SUM($F$5:$F$27),0)
A14: 10 | B14: =IF(A14<=4,"R1 Foundation",IF(A14<=8,"R2 Core Clinic",IF(A14<=13,"R3 Revenue & Messaging",IF(A14<=18,"R4 Patient & Platform",IF(A14<=20,"R5 Harden","R6 Launch"))))) | C14: 3 | D14: =C14*README!$B$31 | E14: =COUNTIF(Backlog!$M$2:$M$352,$A14) | F14: =SUMIF(Backlog!$M$2:$M$352,$A14,Backlog!$L$2:$L$352) | G14: =D14-F14 | H14: =IFERROR(F14/D14,0) | I14: =F14*README!$B$32 | J14: =COUNTIFS(Backlog!$M$2:$M$352,$A14,Backlog!$J$2:$J$352,"Must") | K14: =SUM($F$5:F14) | L14: =IFERROR(K14/SUM($F$5:$F$27),0)
A15: 11 | B15: =IF(A15<=4,"R1 Foundation",IF(A15<=8,"R2 Core Clinic",IF(A15<=13,"R3 Revenue & Messaging",IF(A15<=18,"R4 Patient & Platform",IF(A15<=20,"R5 Harden","R6 Launch"))))) | C15: 3 | D15: =C15*README!$B$31 | E15: =COUNTIF(Backlog!$M$2:$M$352,$A15) | F15: =SUMIF(Backlog!$M$2:$M$352,$A15,Backlog!$L$2:$L$352) | G15: =D15-F15 | H15: =IFERROR(F15/D15,0) | I15: =F15*README!$B$32 | J15: =COUNTIFS(Backlog!$M$2:$M$352,$A15,Backlog!$J$2:$J$352,"Must") | K15: =SUM($F$5:F15) | L15: =IFERROR(K15/SUM($F$5:$F$27),0)
A16: 12 | B16: =IF(A16<=4,"R1 Foundation",IF(A16<=8,"R2 Core Clinic",IF(A16<=13,"R3 Revenue & Messaging",IF(A16<=18,"R4 Patient & Platform",IF(A16<=20,"R5 Harden","R6 Launch"))))) | C16: 4 | D16: =C16*README!$B$31 | E16: =COUNTIF(Backlog!$M$2:$M$352,$A16) | F16: =SUMIF(Backlog!$M$2:$M$352,$A16,Backlog!$L$2:$L$352) | G16: =D16-F16 | H16: =IFERROR(F16/D16,0) | I16: =F16*README!$B$32 | J16: =COUNTIFS(Backlog!$M$2:$M$352,$A16,Backlog!$J$2:$J$352,"Must") | K16: =SUM($F$5:F16) | L16: =IFERROR(K16/SUM($F$5:$F$27),0)
... A27: 23 | B27: =IF(A27<=4,"R1 Foundation",IF(A27<=8,"R2 Core Clinic",IF(A27<=13,"R3 Revenue & Messaging",IF(A27<=18,"R4 Patient & Platform",IF(A27<=20,"R5 Harden","R6 Launch"))))) | C27: 2 | D27: =C27*README!$B$31 | E27: =COUNTIF(Backlog!$M$2:$M$352,$A27) | F27: =SUMIF(Backlog!$M$2:$M$352,$A27,Backlog!$L$2:$L$352) | G27: =D27-F27 | H27: =IFERROR(F27/D27,0) | I27: =F27*README!$B$32 | J27: =COUNTIFS(Backlog!$M$2:$M$352,$A27,Backlog!$J$2:$J$352,"Must") | K27: =SUM($F$5:F27) | L27: =IFERROR(K27/SUM($F$5:$F$27),0)
A28: TOTAL | D28: =SUM(D5:D27) | E28: =SUM(E5:E27) | F28: =SUM(F5:F27) | H28: =IFERROR(F28/D28,0) | I28: =SUM(I5:I27) | J28: =SUM(J5:J27)
A30: Programme shape
A31: Elapsed weeks | D31: =README!$B$30*23
A32: Approximate elapsed months | D32: =D31/4.345
A33: Peak squads in parallel | D33: =MAX(C5:C27)
A34: Peak people (approx, 6 per squad) | D34: =D33*6
A35: Indicative cost (only if a day rate is set on README) | D35: =I28*README!$B$33

Sheet Tracks
A1: Parallel delivery tracks
A2: This programme cannot be delivered by one team. These are the four workstreams the backlog naturally separates into.
A4: Track | B4: What it covers | C4: Tasks | D4: Story Points | E4: % of Points | F4: Est. Person-Days | G4: First Sprint | H4: Last Sprint
A5: Shared | B5: Foundation, design system, charts, i18n, auth, security, DevOps and QA — everything the other three depend on | C5: =COUNTIF(Backlog!$H$2:$H$352,$A5) | D5: =SUMIF(Backlog!$H$2:$H$352,$A5,Backlog!$L$2:$L$352) | E5: =IFERROR(D5/$D$9,0) | F5: =D5*README!$B$32 | G5: =_xlfn.MINIFS(Backlog!$M$2:$M$352,Backlog!$H$2:$H$352,$A5) | H5: =_xlfn.MAXIFS(Backlog!$M$2:$M$352,Backlog!$H$2:$H$352,$A5)
A6: Clinic | B6: Reception, doctor, nurse and owner surfaces: queue, clinical, billing, packages, pharmacy, reports | C6: =COUNTIF(Backlog!$H$2:$H$352,$A6) | D6: =SUMIF(Backlog!$H$2:$H$352,$A6,Backlog!$L$2:$L$352) | E6: =IFERROR(D6/$D$9,0) | F6: =D6*README!$B$32 | G6: =_xlfn.MINIFS(Backlog!$M$2:$M$352,Backlog!$H$2:$H$352,$A6) | H6: =_xlfn.MAXIFS(Backlog!$M$2:$M$352,Backlog!$H$2:$H$352,$A6)
A7: Patient | B7: The WhatsApp patient surface, caregiver and family handling, messaging infrastructure and the aggregator | C7: =COUNTIF(Backlog!$H$2:$H$352,$A7) | D7: =SUMIF(Backlog!$H$2:$H$352,$A7,Backlog!$L$2:$L$352) | E7: =IFERROR(D7/$D$9,0) | F7: =D7*README!$B$32 | G7: =_xlfn.MINIFS(Backlog!$M$2:$M$352,Backlog!$H$2:$H$352,$A7) | H7: =_xlfn.MAXIFS(Backlog!$M$2:$M$352,Backlog!$H$2:$H$352,$A7)
A8: Platform | B8: The SaaS console: provisioning, operator roles, subscriptions, support, health, territories and growth | C8: =COUNTIF(Backlog!$H$2:$H$352,$A8) | D8: =SUMIF(Backlog!$H$2:$H$352,$A8,Backlog!$L$2:$L$352) | E8: =IFERROR(D8/$D$9,0) | F8: =D8*README!$B$32 | G8: =_xlfn.MINIFS(Backlog!$M$2:$M$352,Backlog!$H$2:$H$352,$A8) | H8: =_xlfn.MAXIFS(Backlog!$M$2:$M$352,Backlog!$H$2:$H$352,$A8)
A9: TOTAL | C9: =SUM(C5:C8) | D9: =SUM(D5:D8) | E9: =SUM(E5:E8) | F9: =SUM(F5:F8)

Sheet RBAC Matrix
A1: Clinic role & permission matrix — specification for epic E06
A2: Taken from the wireframe permission model. Y granted, N not granted, P plan/subscription dependent, - not applicable.
A3: Rule: a permission-restricted element is ABSENT, never disabled or greyed. Enforcement is server-side; the UI only reflects it. Consent is additionally checked at query level (NFR-08).
A5: Role | B5: Module | C5: View | D5: Create | E5: Edit | F5: Delete / Void | G5: Approve | H5: Refund / Discount | I5: Export | J5: Notes
A6: Owner / Manager | B6: Patients | C6: Y | D6: Y | E6: Y | F6: Y | G6: Y | H6: - | I6: Y
B7: Queue & Appointments | C7: Y | D7: Y | E7: Y | F7: Y | G7: Y | H7: - | I7: Y
B8: Clinical Records | C8: Y | D8: N | E8: N | F8: Y | G8: Y | H8: - | I8: Y
B9: Billing & Payments | C9: Y | D9: Y | E9: Y | F9: Y | G9: Y | H9: Y | I9: Y
B10: Packages | C10: Y | D10: Y | E10: Y | F10: Y | G10: Y | H10: Y | I10: Y
B11: Pharmacy | C11: P | D11: P | E11: P | F11: P | G11: P | H11: P | I11: P | J11: Pharmacy availability follows the tenant plan and pharmacy mode (CAD-11), not the role.
B12: Reports | C12: Y | D12: - | E12: - | F12: - | G12: Y | H12: - | I12: Y
B13: Staff & Access | C13: Y | D13: Y | E13: Y | F13: Y | G13: Y | H13: - | I13: Y
B14: Clinic Setup | C14: Y | D14: - | E14: Y | F14: - | G14: - | H14: - | I14: Y
B15: Compliance & Audit | C15: Y | D15: - | E15: - | F15: Y | G15: Y | H15: - | I15: Y
A16: Doctor | B16: Patients | C16: Y | D16: Y | E16: Y | F16: - | G16: N | H16: - | I16: - | J16: Scope is per staff member: own patients only, or all clinic patients. Enforced in the query (E06).
B17: Queue & Appointments | C17: Y | D17: - | E17: Y | F17: - | G17: - | H17: - | I17: -
B18: Clinical Records | C18: Y | D18: Y | E18: Y | F18: Y | G18: N | H18: - | I18: -
B19: Billing & Payments | C19: Y | D19: - | E19: - | F19: - | G19: - | H19: - | I19: -
B20: Packages | C20: Y | D20: Y | E20: Y | F20: - | G20: - | H20: - | I20: -
B21: Pharmacy | C21: P | D21: P | E21: N | F21: - | G21: - | H21: - | I21: - | J21: External mode removes dispensing entirely; hybrid and in-house are paid tiers.
B22: Reports | C22: Y | D22: - | E22: - | F22: - | G22: N | H22: - | I22: -
B23: Staff & Access | C23: N | D23: - | E23: - | F23: - | G23: - | H23: - | I23: -
B24: Clinic Setup | C24: N | D24: - | E24: - | F24: - | G24: - | H24: - | I24: -
B25: Compliance & Audit | C25: N | D25: - | E25: - | F25: - | G25: - | H25: - | I25: -
A26: Receptionist | B26: Patients | C26: Y | D26: Y | E26: Y | F26: - | G26: N | H26: - | I26: -
B27: Queue & Appointments | C27: Y | D27: Y | E27: Y | F27: - | G27: - | H27: - | I27: -
B28: Clinical Records | C28: N | D28: - | E28: - | F28: - | G28: - | H28: - | I28: -
B29: Billing & Payments | C29: Y | D29: Y | E29: Y | F29: N | G29: Y | H29: N | I29: - | J29: Refund and discount rights are individually revocable — the wireframe shows a 'no refund, no discount' receptionist.
B30: Packages | C30: Y | D30: Y | E30: N | F30: - | G30: - | H30: - | I30: -
B31: Pharmacy | C31: P | D31: P | E31: N | F31: - | G31: - | H31: - | I31: -
B32: Reports | C32: N | D32: - | E32: - | F32: - | G32: - | H32: - | I32: -
B33: Staff & Access | C33: N | D33: - | E33: - | F33: - | G33: - | H33: - | I33: -
B34: Clinic Setup | C34: N | D34: - | E34: - | F34: - | G34: - | H34: - | I34: -
B35: Compliance & Audit | C35: N | D35: - | E35: - | F35: - | G35: - | H35: - | I35: -
A36: Nurse | B36: Patients | C36: Y | D36: N | E36: Y | F36: - | G36: N | H36: - | I36: -
B37: Queue & Appointments | C37: Y | D37: - | E37: Y | F37: - | G37: - | H37: - | I37: -
B38: Clinical Records | C38: Y | D38: Y | E38: Y | F38: - | G38: N | H38: - | I38: - | J38: May be narrowed to vitals and vaccines only.
B39: Billing & Payments | C39: N | D39: - | E39: - | F39: - | G39: - | H39: - | I39: -
B40: Packages | C40: Y | D40: - | E40: Y | F40: - | G40: - | H40: - | I40: -
B41: Pharmacy | C41: P | D41: N | E41: N | F41: - | G41: - | H41: - | I41: -
B42: Reports | C42: N | D42: - | E42: - | F42: - | G42: - | H42: - | I42: -
B43: Staff & Access | C43: N | D43: - | E43: - | F43: - | G43: - | H43: - | I43: -
B44: Clinic Setup | C44: N | D44: - | E44: - | F44: - | G44: - | H44: - | I44: -
B45: Compliance & Audit | C45: N | D45: - | E45: - | F45: - | G45: - | H45: - | I45: -
A46: Custom (Front Desk + Vitals) | B46: Patients | C46: Y | D46: Y | E46: Y | F46: - | G46: N | H46: - | I46: -
B47: Queue & Appointments | C47: Y | D47: Y | E47: Y | F47: - | G47: - | H47: - | I47: -
B48: Clinical Records | C48: Y | D48: Y | E48: N | F48: - | G48: N | H48: - | I48: -
B49: Billing & Payments | C49: Y | D49: Y | E49: Y | F49: N | G49: Y | H49: N | I49: - | J49: The wireframe's example custom role: 'no financial fields'.
B50: Packages | C50: Y | D50: Y | E50: N | F50: - | G50: - | H50: - | I50: -
B51: Pharmacy | C51: P | D51: P | E51: N | F51: - | G51: - | H51: - | I51: -
B52: Reports | C52: N | D52: - | E52: - | F52: - | G52: - | H52: - | I52: -
B53: Staff & Access | C53: N | D53: - | E53: - | F53: - | G53: - | H53: - | I53: -
B54: Clinic Setup | C54: N | D54: - | E54: - | F54: - | G54: - | H54: - | I54: -
B55: Compliance & Audit | C55: N | D55: - | E55: - | F55: - | G55: - | H55: - | I55: -

Sheet SaaS Operator Roles
A1: Platform-side operator roles (SSA-02) — specification for epic E22
A2: Seven roles. No single super-admin does everything. A role without create rights has no create button anywhere — the element is absent, not disabled.
A4: Surface | B4: Super admin | C4: Implementation | D4: Support engineer | E4: Billing | F4: SRE | G4: Commercial (read-only) | H4: Compliance / DPO
A5: Command Centre | B5: Y | C5: Y | D5: Y | E5: Y | F5: Y | G5: Y | H5: Y
A6: Clinics / fleet | B6: Y | C6: Y | D6: Y | E6: Y | F6: — | G6: Y | H6: Y
A7: Tenant detail | B7: Y | C7: Y | D7: Y | E7: — | F7: — | G7: — | H7: Y
A8: Onboarding / provisioning | B8: Y | C8: Y | D8: — | E8: — | F8: — | G8: — | H8: —
A9: Provisioning jobs | B9: Y | C9: Y | D9: — | E9: — | F9: Y | G9: — | H9: —
A10: Billing & revenue | B10: Y | C10: — | D10: — | E10: Y | F10: — | G10: Y | H10: —
A11: Support tickets | B11: Y | C11: Y | D11: Y | E11: — | F11: — | G11: — | H11: —
A12: Pricing & packaging | B12: Y | C12: — | D12: — | E12: Y | F12: — | G12: — | H12: —
A13: Territories | B13: Y | C13: — | D13: — | E13: — | F13: Y | G13: Y | H13: Y
A14: Messaging operations | B14: Y | C14: Y | D14: — | E14: — | F14: Y | G14: — | H14: —
A15: Platform health | B15: Y | C15: — | D15: Y | E15: — | F15: Y | G15: — | H15: —
... A18: Audit & compliance | B18: Y | C18: — | D18: — | E18: — | F18: Y | G18: — | H18: Y
A20: Hard rules from the wireframe
A21: • Only Super admin and Implementation may create a tenant. For every other role no create button exists anywhere (SSA-02).
A22: • A support engineer never sees clinical fields — the same restricted overlay the clinic itself sees (SSA-04).
A23: • Support access into a tenant requires consent, is time-boxed, shows the tenant a banner, and is fully audited.
A24: • Commercial is read-only by construction, not by convention.
A25: • Compliance / DPO reaches audit and residency surfaces but not billing or provisioning.

Sheet Security Controls
A1: Cybersecurity, privacy and compliance control checklist
A2: Each control names the backlog task that delivers it. Use this as the pre-go-live gate.
A4: Domain | B4: Control | C4: Delivered by | D4: Task ID | E4: Priority | F4: Gate | G4: Verified? | H4: Evidence / Link
A5: Identity | B5: Staff sign-in limited to WhatsApp OTP, short PIN or authenticator app — no SSO, no hardware keys (NFR-06) | C5: Staff authentication — WhatsApp OTP | D5: NB-040 | E5: Must | F5: Go-live blocker | G5: No
A6: Identity | B6: Verified email and mobile both required before any patient data is reachable (CAD-12) | C6: Dual-channel staff identity | D6: NB-041 | E6: Must | F6: Go-live blocker | G6: No
A7: Identity | B7: Authenticator MFA enforced for Owner, Platform operators and refund/discount holders | C7: Authenticator-app MFA enforcement | D7: NB-042 | E7: Must | F7: Go-live blocker | G7: No
A8: Identity | B8: Short-lived tokens, rotating refresh, reuse detection, remote session revoke | C8: Session management & device trust | D8: NB-043 | E8: Must | F8: Go-live blocker | G8: No
A9: Identity | B9: Shared-workstation auto-lock without losing draft clinical notes | C9: Idle timeout & clinical screen lock | D9: NB-044 | E9: Must | F9: Go-live blocker | G9: No
A10: Identity | B10: Break-glass access is time-boxed, reason-captured and loudly alerted | C10: Break-glass emergency access | D10: NB-048 | E10: Should | F10: Post-launch acceptable | G10: No
A11: Access control | B11: Deny-by-default server-side authorisation on every endpoint | C11: Server-side policy enforcement point | D11: NB-050 | E11: Must | F11: Go-live blocker | G11: No
A12: Access control | B12: Row-level patient scoping enforced in the query, not by post-filtering | C12: Row-level scoping | D12: NB-051 | E12: Must | F12: Go-live blocker | G12: No
A13: Access control | B13: Field-level restrictions applied in the API response, not merely hidden in the UI | C13: Field-level restrictions | D13: NB-052 | E13: Must | F13: Go-live blocker | G13: No
A14: Access control | B14: Consent evaluated at query level — the UI is not the enforcement point (NFR-08) | C14: Consent checked at query level | D14: NB-053 | E14: Must | F14: Go-live blocker | G14: No
A15: Access control | B15: Maker-checker on refunds, large discounts and clinical amendments | C15: Approval workflows & maker-checker | D15: NB-056 | E15: Must | F15: Go-live blocker | G15: No
A16: Access control | B16: Restricted elements are absent from the UI, never disabled | C16: UI permission rendering contract | D16: NB-054 | E16: Must | F16: Go-live blocker | G16: No
... A71: People | B71: Security awareness and clinical data handling training completed by all staff | C71: Staff security awareness & data handling | D71: NB-348 | E71: Should | F71: Before pilot | G71: No
A73: Go-live gate | B73: Blocking controls outstanding | D73: =COUNTIFS(F5:F71,"Go-live blocker*",G5:G71,"<>Yes")
B74: Controls verified | D74: =COUNTIF(G5:G71,"Yes")&" of "&COUNTA(B5:B71)

Sheet Risks
A1: Delivery, security and clinical-safety risks
A3: ID | B3: Category | C3: Risk | D3: Impact (1-5) | E3: Likelihood (1-5) | F3: Score | G3: Mitigation | H3: Related Tasks | I3: Owner
A4: R-01 | B4: Clinical safety | C4: A prescribing, dosing or allergy defect reaches production and causes patient harm. | D4: 5 | E4: 3 | F4: =D4*E4 | G4: Clinical safety test suite and hazard log signed by a clinical safety officer; mandatory override reasons; validated dose rule source; staged pilot rollout. | H4: NB-321, NB-108, NB-112 | I4: Clinical Lead
A5: R-02 | B5: Clinical safety | C5: The aggregator routes an emergency to a clinic instead of emergency services. | D5: 5 | E5: 2 | F5: =D5*E5 | G5: Emergency phrase interception in every supported language runs before any routing; Nabd never interprets symptoms; unmatched input goes to reception, not a guess. | H5: NB-222, NB-223 | I5: Clinical Lead
A6: R-03 | B6: Security | C6: Cross-tenant or cross-region leakage breaches PDPL residency rules. | D6: 5 | E6: 3 | F6: =D6*E6 | G6: Isolation proven by PoC in sprint 1; region locked irreversibly at provisioning; region-scoped KMS; no cross-region replication; independent penetration test per region. | H6: NB-002, NB-271, NB-295 | I6: Security Lead
A7: R-04 | B7: Security | C7: The public aggregator number becomes an attack and enumeration surface. | D7: 4 | E7: 3 | F7: =D7*E7 | G7: Per-number and per-IP rate limiting, re-verification on number change before any data release, and abuse monitoring from day one of the aggregator build. | H7: NB-288, NB-289 | I7: Security Lead
A8: R-05 | B8: Vendor | C8: Meta rejects templates, throttles quality or delays WhatsApp onboarding, stalling the patient product. | D8: 5 | E8: 4 | F8: =D8*E8 | G8: Managed onboarding started in sprint 9 ahead of patient build; fleet quality monitoring; automatic SMS fallback; no clinical journey is ever blocked on messaging. | H8: NB-188, NB-264, NB-193 | I8: Integration Lead
A9: R-06 | B9: Compliance | C9: ZATCA Phase-2 e-invoicing rejects invoices and blocks billing in Saudi Arabia. | D9: 5 | E9: 3 | F9: =D9*E9 | G9: Build against the ZATCA sandbox from sprint 12; validate with the official compliance tool; independent tax test pack; manual invoice fallback retained. | H9: NB-164, NB-322 | I9: Finance / Tech Lead
A10: R-07 | B10: Compliance | C10: India GST treatment of clinical services is misapplied, creating tax exposure. | D10: 4 | E10: 3 | F10: =D10*E10 | G10: Independent tax review of the GST engine; effective-dated rate tables; worked-example test pack reproduced to the paisa. | H10: NB-163, NB-322 | I10: Finance Lead
A11: R-08 | B11: Compliance | C11: India DLT registration delays block all messaging to Indian patients. | D11: 4 | E11: 4 | F11: =D11*E11 | G11: Start DLT registration in parallel with the messaging build in sprint 13; keep templates minimal and stable; SMS fallback also requires DLT, so treat it as a single critical path. | H11: NB-194 | I11: Integration Lead
A12: R-09 | B12: Delivery | C12: Scope is roughly double v1 and cannot be absorbed by a single team. | D12: 5 | E12: 4 | F12: =D12*E12 | G12: Four explicit delivery tracks; squad ramp published on the Sprints tab peaking at five squads; Phase 2 and Phase 3 items are separately funded and can be cut without touching MVP. | H12: NB-343 | I12: Delivery Manager
A13: R-10 | B13: Delivery | C13: Nine clinical specialties are treated as one workstream and swamp the clinical track. | D13: 4 | E13: 4 | F13: =D13*E13 | G13: Specialty profile framework first, then one specialty at a time behind an entitlement flag; ENT, Ayurveda and Homeopathy are Phase 2 and droppable. | H13: NB-121, NB-122 | I13: Product Owner
A14: R-11 | B14: Delivery | C14: RBAC complexity — twelve roles across clinic and platform — is underestimated. | D14: 4 | E14: 4 | F14: =D14*E14 | G14: Permission model built in sprint 4 before feature work; automated role-by-endpoint negative-test suite covering all twelve roles from sprint 12. | H14: NB-049, NB-257, NB-317 | I14: Tech Lead
A15: R-12 | B15: Product | C15: The patient WhatsApp journey exceeds its tap budget and patients abandon booking. | D15: 4 | E15: 3 | F15: =D15*E15 | G15: Tap budgets are asserted automatically in the conversation test harness, not reviewed by eye; single-member numbers never see a picker. | H15: NB-202, NB-316 | I15: Product Owner
... A23: R-20 | B23: Vendor | C23: Payment gateway, lab or growth-service partners change their API mid-build. | D23: 3 | E23: 3 | F23: =D23*E23 | G23: An anti-corruption layer per integration; mock harness in CI; contract tests against provider sandboxes; growth percentiles deliberately delegated to a validated service. | H23: NB-168, NB-132 | I23: Integration Lead
A25: Score = Impact x Likelihood. 15 and above is red and needs an active mitigation owner reporting weekly.

Sheet Changes from v1
A1: What changed when the wireframe was updated
A2: v1 (11 Aug): 202 tasks / 1,210 points. v2 (13 Aug): 349 tasks / 2,260 points.
A4: Change | B4: Type | C4: Detail | D4: Impact
A5: Requirement register introduced | B5: Added | C5: The wireframe now carries 185 formal requirement identifiers across 30 prefixes. Every task is traced to them and the Requirement Coverage tab proves complete coverage. | D5: New traceability tab; a Requirement IDs column on every task
A6: Patient WhatsApp surface | B6: Added | C6: PAT-01 to PAT-26. The patient product is a WhatsApp conversation, not a web portal — registration, booking, queue, payments, documents, privacy and language all in chat. | D6: New epic E18, 20 tasks, 128 points
A7: Caregiver, family & guardianship | B7: Added | C7: CGV-01 to CGV-10. One number for a whole family, proxy booking, dual delivery, revocation, age-18 handover and family plans. | D7: New epic E09, 10 tasks, 65 points
A8: Aggregator & demand layer | B8: Added | C8: AGG-01 to AGG-05. A shared Nabd number with invisible routing, emergency interception, word-to-specialty matching and verified-visit ratings. | D8: New epic E19, 7 tasks, 56 points
A9: Platform console rebuilt | B9: Expanded | C9: Seven segregated SaaS operator roles, provisioning as a resumable job queue rather than a wizard, subscriptions and dunning, discount approvals, support tickets with SLA, platform health and territories. | D9: E22 grew from 10 tasks to 18
A10: Chart & data-visualisation system | B10: Added | C10: DESIGN.md 8.22-8.29: an eight-slot series palette, all-pairs colour gate, inline SVG only, ten mandatory chart states and a table view for every chart. | D10: New epic E03, 8 tasks, 49 points
A11: Messaging component set & infrastructure | B11: Added | C11: DESIGN.md 8.16-8.21 plus managed WhatsApp onboarding, template governance, 24-hour session windows, delivery states, SMS fallback and India DLT. | D11: New epic E17, 13 tasks, 100 points
A12: Pharmacy properly specified | B12: Expanded | C12: PHR-01 to PHR-12 with three modes (external, hybrid, in-house), FEFO batch handling, controlled-drug register, refills and adherence capture. | D12: Was one deferred task in v1; now epic E16 with 11 tasks
A13: Compliance & data protection deepened | B13: Expanded | C13: CMP-01 to CMP-12 and DPO-01 to DPO-09: consent template library, consent as a hard gate, DSR engine with statutory timers, retention engine, breach ops, licence tracker and child-data controls. | D13: E21 grew from 8 tasks to 19
A14: Specialty workspaces broken out | B14: Expanded | C14: Nine specialties now specified individually: Dental (FDI storage, radiographs, staging, orthodontics, per-tooth timeline), Dermatology, Paediatrics, General practice, Orthopaedics, Gynaecology, ENT, Ayurveda and Homeopathy. | D14: Was one 13-point task; now epic E12 with 21 tasks
A15: Clinic setup & administration | B15: Added | C15: CAD-01 to CAD-13: a skippable, resumable, fully self-serve setup wizard, price master, policy settings, shift timings and self-serve import/export. | D15: New epic E07, 11 tasks
... A28: Delivery model changed | B28: Changed | C28: v1 assumed a single 8-9 person team over 18 sprints. v2 needs four parallel tracks ramping to five squads (roughly 30 people) across 23 sprints. | D28: New Tracks tab; squad ramp on the Sprints tab
